register_file.sv
module resgister_file #(
    parameter ADDR_WIDTH = 5,
              DATA_WIDTH = 32
)(
    input  logic                 clk,
    input  logic[ADDR_WIDTH-1:0] ad1,
    input  logic[ADDR_WIDTH-1:0] ad2,
    input  logic[ADDR_WIDTH-1:0] ad3,
    output logic[DATA_WIDTH-1:0] rd1,
    output logic[DATA_WIDTH-1:0] rd2,
    input  logic[DATA_WIDTH-1:0] wd3,
    input  logic                 we3,
    output logic[DATA_WIDTH-1:0] a0
);
    
logic[DATA_WIDTH-1:0] registers[ADDR_WIDTH-1:0];

always_comb begin
    rd1 = registers[ad1];
    rd2 = registers[ad2];
    a0 = registers[0];
end

always_ff @(posedge clk) begin
    if(we3) registers[ad3] <= wd3;
end

endmodule

register/register_file.vcd
$version Generated by VerilatedVcd $end
$date Fri Nov 25 11:42:12 2022 $end
$timescale 1ps $end

 $scope module TOP $end
  $var wire 32 K a0 [31:0] $end
  $var wire  5 D ad1 [4:0] $end
  $var wire  5 E ad2 [4:0] $end
  $var wire  5 F ad3 [4:0] $end
  $var wire  1 C clk $end
  $var wire 32 G rd1 [31:0] $end
  $var wire 32 H rd2 [31:0] $end
  $var wire 32 I wd3 [31:0] $end
  $var wire  1 J we3 $end
  $scope module resgister_file $end
   $var wire 32 L ADDR_WIDTH [31:0] $end
   $var wire 32 M DATA_WIDTH [31:0] $end
   $var wire 32 K a0 [31:0] $end
   $var wire  5 D ad1 [4:0] $end
   $var wire  5 E ad2 [4:0] $end
   $var wire  5 F ad3 [4:0] $end
   $var wire  1 C clk $end
   $var wire 32 G rd1 [31:0] $end
   $var wire 32 H rd2 [31:0] $end
   $var wire 32 # registers[0] [31:0] $end
   $var wire 32 - registers[10] [31:0] $end
   $var wire 32 . registers[11] [31:0] $end
   $var wire 32 / registers[12] [31:0] $end
   $var wire 32 0 registers[13] [31:0] $end
   $var wire 32 1 registers[14] [31:0] $end
   $var wire 32 2 registers[15] [31:0] $end
   $var wire 32 3 registers[16] [31:0] $end
   $var wire 32 4 registers[17] [31:0] $end
   $var wire 32 5 registers[18] [31:0] $end
   $var wire 32 6 registers[19] [31:0] $end
   $var wire 32 $ registers[1] [31:0] $end
   $var wire 32 7 registers[20] [31:0] $end
   $var wire 32 8 registers[21] [31:0] $end
   $var wire 32 9 registers[22] [31:0] $end
   $var wire 32 : registers[23] [31:0] $end
   $var wire 32 ; registers[24] [31:0] $end
   $var wire 32 < registers[25] [31:0] $end
   $var wire 32 = registers[26] [31:0] $end
   $var wire 32 > registers[27] [31:0] $end
   $var wire 32 ? registers[28] [31:0] $end
   $var wire 32 @ registers[29] [31:0] $end
   $var wire 32 % registers[2] [31:0] $end
   $var wire 32 A registers[30] [31:0] $end
   $var wire 32 B registers[31] [31:0] $end
   $var wire 32 & registers[3] [31:0] $end
   $var wire 32 ' registers[4] [31:0] $end
   $var wire 32 ( registers[5] [31:0] $end
   $var wire 32 ) registers[6] [31:0] $end
   $var wire 32 * registers[7] [31:0] $end
   $var wire 32 + registers[8] [31:0] $end
   $var wire 32 , registers[9] [31:0] $end
   $var wire 32 I wd3 [31:0] $end
   $var wire  1 J we3 $end
  $upscope $end
 $upscope $end
$enddefinitions $end


#0
b00000000000000000000000000000000 #
b00000000000000000000000000000000 $
b00000000000000000000000000000000 %
b00000000000000000000000000000000 &
b00000000000000000000000000000000 '
b00000000000000000000000000000000 (
b00000000000000000000000000000000 )
b00000000000000000000000000000000 *
b00000000000000000000000000000000 +
b00000000000000000000000000000000 ,
b00000000000000000000000000000000 -
b00000000000000000000000000000000 .
b00000000000000000000000000000000 /
b00000000000000000000000000000000 0
b00000000000000000000000000000000 1
b00000000000000000000000000000000 2
b00000000000000000000000000000000 3
b00000000000000000000000000000000 4
b00000000000000000000000000000000 5
b00000000000000000000000000000000 6
b00000000000000000000000000000000 7
b00000000000000000000000000000000 8
b00000000000000000000000000000000 9
b00000000000000000000000000000000 :
b00000000000000000000000000000000 ;
b00000000000000000000000000000000 <
b00000000000000000000000000000000 =
b00000000000000000000000000000000 >
b00000000000000000000000000000000 ?
b00000000000000000000000000000000 @
b00000000000000000000000000000000 A
b00000000000000000000000000000000 B
1C
b11111 D
b00000 E
b00000 F
b00000000000000000000000000000000 G
b00000000000000000000000000000000 H
b00000000000000000000000000000000 I
1J
b00000000000000000000000000000000 K
b00000000000000000000000000000101 L
b00000000000000000000000000100000 M
#1
0C
#2
1C
b00000 D
b00001 E
b00001 F
b00000000000000000000000000000001 I
#3
b00000000000000000000000000000001 $
0C
b00000000000000000000000000000001 H
#4
1C
b00001 D
b00010 E
b00010 F
b00000000000000000000000000000001 G
b00000000000000000000000000000000 H
b00000000000000000000000000000010 I
#5
b00000000000000000000000000000010 %
0C
b00000000000000000000000000000010 H
#6
1C
b00010 D
b00011 E
b00011 F
b00000000000000000000000000000010 G
b00000000000000000000000000000000 H
b00000000000000000000000000000011 I
#7
b00000000000000000000000000000011 &
0C
b00000000000000000000000000000011 H
#8
1C
b00011 D
b00100 E
b00100 F
b00000000000000000000000000000011 G
b00000000000000000000000000000000 H
b00000000000000000000000000000100 I
#9
b00000000000000000000000000000100 '
0C
b00000000000000000000000000000100 H
#10
1C
b00100 D
b00101 E
b00101 F
b00000000000000000000000000000100 G
b00000000000000000000000000000000 H
b00000000000000000000000000000101 I
#11
b00000000000000000000000000000101 (
0C
b00000000000000000000000000000101 H
#12
1C
b00101 D
b00110 E
b00110 F
b00000000000000000000000000000101 G
b00000000000000000000000000000000 H
b00000000000000000000000000000110 I
#13
b00000000000000000000000000000110 )
0C
b00000000000000000000000000000110 H
#14
1C
b00110 D
b00111 E
b00111 F
b00000000000000000000000000000110 G
b00000000000000000000000000000000 H
b00000000000000000000000000000111 I
#15
b00000000000000000000000000000111 *
0C
b00000000000000000000000000000111 H
#16
1C
b00111 D
b01000 E
b01000 F
b00000000000000000000000000000111 G
b00000000000000000000000000000000 H
b00000000000000000000000000001000 I
#17
b00000000000000000000000000001000 +
0C
b00000000000000000000000000001000 H
#18
1C
b01000 D
b01001 E
b01001 F
b00000000000000000000000000001000 G
b00000000000000000000000000000000 H
b00000000000000000000000000001001 I
#19
b00000000000000000000000000001001 ,
0C
b00000000000000000000000000001001 H
#20
1C
b01001 D
b01010 E
b01010 F
b00000000000000000000000000001001 G
b00000000000000000000000000000000 H
b00000000000000000000000000001010 I
#21
b00000000000000000000000000001010 -
0C
b00000000000000000000000000001010 H
b00000000000000000000000000001010 K
#22
1C
b01010 D
b01011 E
b01011 F
b00000000000000000000000000001010 G
b00000000000000000000000000000000 H
b00000000000000000000000000001011 I
#23
b00000000000000000000000000001011 .
0C
b00000000000000000000000000001011 H
#24
1C
b01011 D
b01100 E
b01100 F
b00000000000000000000000000001011 G
b00000000000000000000000000000000 H
b00000000000000000000000000001100 I
#25
b00000000000000000000000000001100 /
0C
b00000000000000000000000000001100 H
#26
1C
b01100 D
b01101 E
b01101 F
b00000000000000000000000000001100 G
b00000000000000000000000000000000 H
b00000000000000000000000000001101 I
#27
b00000000000000000000000000001101 0
0C
b00000000000000000000000000001101 H
#28
1C
b01101 D
b01110 E
b01110 F
b00000000000000000000000000001101 G
b00000000000000000000000000000000 H
b00000000000000000000000000001110 I
#29
b00000000000000000000000000001110 1
0C
b00000000000000000000000000001110 H
#30
1C
b01110 D
b01111 E
b01111 F
b00000000000000000000000000001110 G
b00000000000000000000000000000000 H
b00000000000000000000000000001111 I
#31
b00000000000000000000000000001111 2
0C
b00000000000000000000000000001111 H
#32
1C
b01111 D
b10000 E
b10000 F
b00000000000000000000000000001111 G
b00000000000000000000000000000000 H
b00000000000000000000000000010000 I
#33
b00000000000000000000000000010000 3
0C
b00000000000000000000000000010000 H
#34
1C
b10000 D
b10001 E
b10001 F
b00000000000000000000000000010000 G
b00000000000000000000000000000000 H
b00000000000000000000000000010001 I
#35
b00000000000000000000000000010001 4
0C
b00000000000000000000000000010001 H
#36
1C
b10001 D
b10010 E
b10010 F
b00000000000000000000000000010001 G
b00000000000000000000000000000000 H
b00000000000000000000000000010010 I
#37
b00000000000000000000000000010010 5
0C
b00000000000000000000000000010010 H
#38
1C
b10010 D
b10011 E
b10011 F
b00000000000000000000000000010010 G
b00000000000000000000000000000000 H
b00000000000000000000000000010011 I
#39
b00000000000000000000000000010011 6
0C
b00000000000000000000000000010011 H
#40
1C
b10011 D
b10100 E
b10100 F
b00000000000000000000000000010011 G
b00000000000000000000000000000000 H
b00000000000000000000000000010100 I
#41
b00000000000000000000000000010100 7
0C
b00000000000000000000000000010100 H
#42
1C
b10100 D
b10101 E
b10101 F
b00000000000000000000000000010100 G
b00000000000000000000000000000000 H
b00000000000000000000000000010101 I
#43
b00000000000000000000000000010101 8
0C
b00000000000000000000000000010101 H
#44
1C
b10101 D
b10110 E
b10110 F
b00000000000000000000000000010101 G
b00000000000000000000000000000000 H
b00000000000000000000000000010110 I
#45
b00000000000000000000000000010110 9
0C
b00000000000000000000000000010110 H
#46
1C
b10110 D
b10111 E
b10111 F
b00000000000000000000000000010110 G
b00000000000000000000000000000000 H
b00000000000000000000000000010111 I
#47
b00000000000000000000000000010111 :
0C
b00000000000000000000000000010111 H
#48
1C
b10111 D
b11000 E
b11000 F
b00000000000000000000000000010111 G
b00000000000000000000000000000000 H
b00000000000000000000000000011000 I
#49
b00000000000000000000000000011000 ;
0C
b00000000000000000000000000011000 H
#50
1C
b11000 D
b11001 E
b11001 F
b00000000000000000000000000011000 G
b00000000000000000000000000000000 H
b00000000000000000000000000011001 I
#51
b00000000000000000000000000011001 <
0C
b00000000000000000000000000011001 H
#52
1C
b11001 D
b11010 E
b11010 F
b00000000000000000000000000011001 G
b00000000000000000000000000000000 H
b00000000000000000000000000011010 I
#53
b00000000000000000000000000011010 =
0C
b00000000000000000000000000011010 H
#54
1C
b11010 D
b11011 E
b11011 F
b00000000000000000000000000011010 G
b00000000000000000000000000000000 H
b00000000000000000000000000011011 I
#55
b00000000000000000000000000011011 >
0C
b00000000000000000000000000011011 H
#56
1C
b11011 D
b11100 E
b11100 F
b00000000000000000000000000011011 G
b00000000000000000000000000000000 H
b00000000000000000000000000011100 I
#57
b00000000000000000000000000011100 ?
0C
b00000000000000000000000000011100 H
#58
1C
b11100 D
b11101 E
b11101 F
b00000000000000000000000000011100 G
b00000000000000000000000000000000 H
b00000000000000000000000000011101 I
#59
b00000000000000000000000000011101 @
0C
b00000000000000000000000000011101 H
#60
1C
b11101 D
b11110 E
b11110 F
b00000000000000000000000000011101 G
b00000000000000000000000000000000 H
b00000000000000000000000000011110 I
#61
b00000000000000000000000000011110 A
0C
b00000000000000000000000000011110 H
#62
1C
b11110 D
b11111 E
b11111 F
b00000000000000000000000000011110 G
b00000000000000000000000000000000 H
b00000000000000000000000000011111 I
#63
b00000000000000000000000000011111 B
0C
b00000000000000000000000000011111 H
#64
1C
b11111 D
b00000 E
b00000000000000000000000000011111 G
b00000000000000000000000000000000 H
#65
0C
b00000000000000000000000100000000 H
#66
1C
b00000 D
b00001 E
b00000000000000000000000000000000 G
b00000000000000000000000000000000 H
#67
0C
b00000000000000000000000100000000 G
#68
1C
b00001 D
b00010 E
b00000000000000000000000000000000 G
b01001000111000000100010011000000 H
#69
0C
#70
1C
b00010 D
b00011 E
b01001000111000000100010011000000 G
b00000000000000000000000000000001 H
#71
0C
#72
1C
b00011 D
b00100 E
b00000000000000000000000000000001 G
b00000000000000000000000000000000 H
#73
0C
#74
1C
b00100 D
b00101 E
b00000000000000000000000000000000 G
#75
0C
#76
1C
b00101 D
b00110 E
#77
0C
#78
1C
b00110 D
b00111 E
#79
0C
#80
1C
b00111 D
b01000 E
#81
0C
#82
1C
b01000 D
b01001 E
b10100000000000000000000000000000 H
#83
0C
#84
1C
b01001 D
b01010 E
b10100000000000000000000000000000 G
b00000000000000000000000000000000 H
#85
0C
#86
1C
b01010 D
b01011 E
b00000000000000000000000000000000 G
b10100000000000000000000000000000 H
#87
0C
#88
1C
b01011 D
b01100 E
b10100000000000000000000000000000 G
b00000000000000000000000000000011 H
#89
0C
#90
1C
b01100 D
b01101 E
b00000000000000000000000000000011 G
b00000000000000000000000000000000 H
#91
0C
#92
1C
b01101 D
b01110 E
b00000000000000000000000000000000 G
#93
0C
#94
1C
b01110 D
b01111 E
#95
0C
#96
1C
b01111 D
b10000 E
#97
0C
#98
1C
b10000 D
b10001 E
#99
0C
#100
1C
b10001 D
b10010 E
#101
0C
#102
1C
b10010 D
b10011 E
b00000000000000110000000000000000 H
#103
0C
#104
1C
b10011 D
b10100 E
b00000000000000110000000000000000 G
b00000010010100011000010000011000 H
#105
0C
#106
1C
b10100 D
b10101 E
b00000010010100011000010000011000 G
b00000000000000000000000000000001 H
#107
0C
#108
1C
b10101 D
b10110 E
b00000000000000000000000000000001 G
b00000010010100011000010111101000 H
#109
0C
#110
1C
b10110 D
b10111 E
b00000010010100011000010111101000 G
b00000000000000000000000000000001 H
#111
0C
#112
1C
b10111 D
b11000 E
b00000000000000000000000000000001 G
b00000000000000000000000000000000 H
#113
0C
#114
1C
b11000 D
b11001 E
b00000000000000000000000000000000 G
#115
0C
#116
1C
b11001 D
b11010 E
b00000011011011111100000000000000 H
#117
0C
#118
1C
b11010 D
b11011 E
b00000011011011111100000000000000 G
b00000000000000000110000000000000 H
#119
0C
#120
1C
b11011 D
b11100 E
b00000000000000000110000000000000 G
b00000000000000000000000000000000 H
#121
0C
#122
1C
b11100 D
b11101 E
b00000000000000000000000000000000 G
#123
0C
#124
1C
b11101 D
b11110 E
#125
0C
#126
1C
b11110 D
b11111 E
#127
0C
#128
1C
b11111 D
b00000 E
#129
0C
#130
1C
b00000 D
b00001 E
#131
0C
#132
1C
b00001 D
b00010 E
#133
0C
#134
1C
b00010 D
b00011 E
#135
0C
#136
1C
b00011 D
b00100 E
b00000000000111111000000001100000 H
#137
0C
#138
1C
b00100 D
b00101 E
b00000000000111111000000001100000 G
b00000000000000000110000000000000 H
#139
0C
#140
1C
b00101 D
b00110 E
b00000000000000000110000000000000 G
b00000000000111111000000001110000 H
#141
0C
#142
1C
b00110 D
b00111 E
b00000000000111111000000001110000 G
b00000000000000000110000000000000 H
#143
0C
#144
1C
b00111 D
b01000 E
b00000000000000000110000000000000 G
b00000000000111111000000001110000 H
#145
0C
#146
1C
b01000 D
b01001 E
b00000000000111111000000001110000 G
b00000000000000000110000000000000 H
#147
0C
#148
1C
b01001 D
b01010 E
b00000000000000000110000000000000 G
b00000000000111111000000001110000 H
#149
0C
#150
1C
b01010 D
b01011 E
b00000000000111111000000001110000 G
b00000000000000000110000000000000 H
#151
0C
#152
1C
b01011 D
b01100 E
b00000000000000000110000000000000 G
b00000000000111111000000010000000 H
#153
0C
#154
1C
b01100 D
b01101 E
b00000000000111111000000010000000 G
b00000000000000000110000000000000 H
#155
0C
#156
1C
b01101 D
b01110 E
b00000000000000000110000000000000 G
b00000000000111111000000010000000 H
#157
0C
#158
1C
b01110 D
b01111 E
b00000000000111111000000010000000 G
b00000000000000000110000000000000 H
#159
0C
#160
1C
b01111 D
b10000 E
b00000000000000000110000000000000 G
b00000000000000000000000000000000 H
#161
0C
#162
1C
b10000 D
b10001 E
b00000000000000000000000000000000 G
#163
0C
#164
1C
b10001 D
b10010 E
#165
0C
#166
1C
b10010 D
b10011 E
#167
0C
#168
1C
b10011 D
b10100 E
#169
0C
#170
1C
b10100 D
b10101 E
#171
0C
#172
1C
b10101 D
b10110 E
b00000000000111111000000010000000 H
#173
0C
#174
1C
b10110 D
b10111 E
b00000000000111111000000010000000 G
b00000000000000000110000000000000 H
#175
0C
#176
1C
b10111 D
b11000 E
b00000000000000000110000000000000 G
b00000000000111111000000010010000 H
#177
0C
#178
1C
b11000 D
b11001 E
b00000000000111111000000010010000 G
b00000000000000000110000000000000 H
#179
0C
#180
1C
b11001 D
b11010 E
b00000000000000000110000000000000 G
b00000000000111111000000010010000 H
#181
0C
#182
1C
b11010 D
b11011 E
b00000000000111111000000010010000 G
b00000000000000000110000000000000 H
#183
0C
#184
1C
b11011 D
b11100 E
b00000000000000000110000000000000 G
b00000000000000000000000000000000 H
#185
0C
#186
1C
b11100 D
b11101 E
b00000000000000000000000000000000 G
#187
0C
#188
1C
b11101 D
b11110 E
#189
0C
#190
1C
b11110 D
b11111 E
#191
0C
#192
1C
b11111 D
b00000 E
#193
0C
#194
1C
b00000 D
b00001 E
#195
0C
#196
1C
b00001 D
b00010 E
b00000000000111111000000010010000 H
#197
0C
#198
1C
b00010 D
b00011 E
b00000000000111111000000010010000 G
b00000000000000000110000000000000 H
#199
0C
#200
1C
b00011 D
b00100 E
b00000000000000000110000000000000 G
b00000000000111111000000010100000 H
#201
0C
#202
1C
b00100 D
b00101 E
b00000000000111111000000010100000 G
b00000000000000000110000000000000 H
#203
0C
#204
1C
b00101 D
b00110 E
b00000000000000000110000000000000 G
b00000000000111111000000010100000 H
#205
0C
#206
1C
b00110 D
b00111 E
b00000000000111111000000010100000 G
b00000000000000000110000000000000 H
#207
0C
#208
1C
b00111 D
b01000 E
b00000000000000000110000000000000 G
b00000000000000000000000000000000 H
#209
0C
#210
1C
b01000 D
b01001 E
b00000000000000000000000000000000 G
b00000000000000000000000000101101 H
#211
0C
#212
1C
b01001 D
b01010 E
b00000000000000000000000000101101 G
b00000000000000000000000000110100 H
#213
0C
#214
1C
b01010 D
b01011 E
b00000000000000000000000000110100 G
b00000000000000000000000000100000 H
#215
0C
#216
1C
b01011 D
b01100 E
b00000000000000000000000000100000 G
b00000010011111111100000100100000 H
#217
0C
#218
1C
b01100 D
b01101 E
b00000010011111111100000100100000 G
b00000000000000000110000000000000 H
#219
0C
#220
1C
b01101 D
b01110 E
b00000000000000000110000000000000 G
b00000010011111111100000100111000 H
#221
0C
#222
1C
b01110 D
b01111 E
b00000010011111111100000100111000 G
b00000000000000000110000000000000 H
#223
0C
#224
1C
b01111 D
b10000 E
b00000000000000000110000000000000 G
b00000010011111111100000110000000 H
#225
0C
#226
1C
b10000 D
b10001 E
b00000010011111111100000110000000 G
b00000000000000000110000000000000 H
#227
0C
#228
1C
b10001 D
b10010 E
b00000000000000000110000000000000 G
b00000000000000000000000000000000 H
#229
0C
#230
1C
b10010 D
b10011 E
b00000000000000000000000000000000 G
#231
0C
#232
1C
b10011 D
b10100 E
#233
0C
#234
1C
b10100 D
b10101 E
#235
0C
#236
1C
b10101 D
b10110 E
#237
0C
#238
1C
b10110 D
b10111 E
#239
0C
#240
1C
b10111 D
b11000 E
b00000000000000000000000000101110 H
#241
0C
#242
1C
b11000 D
b11001 E
b00000000000000000000000000101110 G
b00000000000000000000000000000000 H
#243
0C
#244
1C
b11001 D
b11010 E
b00000000000000000000000000000000 G
b10000001001011011110101000010001 H
#245
0C
#246
1C
b11010 D
b11011 E
b10000001001011011110101000010001 G
b00111101011100011001011110011001 H
#247
0C
#248
1C
b11011 D
b11100 E
b00111101011100011001011110011001 G
b10000001001011011110101000010001 H
#249
0C
#250
1C
b11100 D
b11101 E
b10000001001011011110101000010001 G
b00111101011100011001011110011001 H
#251
0C
#252
1C
b11101 D
b11110 E
b00111101011100011001011110011001 G
b00000000000000000000000011111011 H
#253
0C
b00000000000000000000000011111100 H
#254
1C
b11110 D
b11111 E
b00000000000000000000000011111101 G
b00000000000000000000000000000000 H
#255
0C
b00000000000000000000000011111110 G
#256
1C
b11111 D
b00000 E
b00000000000000000000000000000000 G
b00000000000000000000000000000001 H
#257
0C
#258
1C
b00000 D
b00001 E
b00000000000000000000000000000001 G
b00000000000000000000000000000000 H
#259
0C
#260
1C
b00001 D
b00010 E
b00000000000000000000000000000000 G
b00000010010100011100000000000000 H
#261
0C
#262
1C
b00010 D
b00011 E
b00000010010100011100000000000000 G
b00000000000000000000000000000001 H
#263
0C
#264
1C
b00011 D
b00100 E
b00000000000000000000000000000001 G
b00000000000111111000000001010000 H
#265
0C
#266
1C
b00100 D
b00101 E
b00000000000111111000000001010000 G
b00000000000000000110000000000000 H
#267
0C
#268
1C
b00101 D
b00110 E
b00000000000000000110000000000000 G
b00000000000000000000000000000010 H
#269
0C
#270
1C
b00110 D
b00111 E
b00000000000000000000000000000010 G
b00000000000000000000000000000000 H
#271
0C
#272
1C
b00111 D
b01000 E
b00000000000000000000000000000000 G
b00000000001111111101000110000000 H
#273
0C
#274
1C
b01000 D
b01001 E
b00000000001111111101000110000000 G
b00000000000000000110000000000000 H
#275
0C
#276
1C
b01001 D
b01010 E
b00000000000000000110000000000000 G
b00000000000000000000000000000001 H
#277
0C
#278
1C
b01010 D
b01011 E
b00000000000000000000000000000001 G
b00000000000000000000000000000000 H
#279
0C
#280
1C
b01011 D
b01100 E
b00000000000000000000000000000000 G
b00111111100000000000000000000000 H
#281
0C
#282
1C
b01100 D
b01101 E
b00111111100000000000000000000000 G
b00000000000000000000000000000000 H
#283
0C
#284
1C
b01101 D
b01110 E
b00000000000000000000000000000000 G
#285
0C
#286
1C
b01110 D
b01111 E
#287
0C
#288
1C
b01111 D
b10000 E
b00000000000111111000000001000000 H
#289
0C
#290
1C
b10000 D
b10001 E
b00000000000111111000000001000000 G
b00000000000000000110000000000000 H
#291
0C
#292
1C
b10001 D
b10010 E
b00000000000000000110000000000000 G
b00000000000000000000000100000001 H
#293
0C
#294
1C
b10010 D
b10011 E
b00000000000000000000000100000001 G
b00000000000000000000000000000000 H
#295
0C
#296
1C
b10011 D
b10100 E
b00000000000000000000000000000000 G
b01101001011001110110010101110010 H
#297
0C
#298
1C
b10100 D
b10101 E
b01101001011001110110010101110010 G
b01110010011001010111010001110011 H
#299
0C
#300
1C
b10101 D
b10110 E
b01110010011001010111010001110011 G
b01101100011010010110011001011111 H
#301
0C
#302
1C
b10110 D
b10111 E
b01101100011010010110011001011111 G
b01100011011101100010111001100101 H
#303
0C
#304
1C
b10111 D
b11000 E
b01100011011101100010111001100101 G
b00000000000000000000000001100100 H
#305
0C
#306
1C
b11000 D
b11001 E
b00000000000000000000000001100100 G
b00010001000000000000000000000000 H
#307
0C
#308
1C
b11001 D
b11010 E
b00010001000000000000000000000000 G
b00000000000000000000000000000000 H
#309
0C
#310
1C
b11010 D
b11011 E
b00000000000000000000000000000000 G
#311
0C
#312
1C
b11011 D
b11100 E
#313
0C
#314
1C
b11100 D
b11101 E
#315
0C
#316
1C
b11101 D
b11110 E
b01010000000000001000000000000000 H
#317
0C
#318
1C
b11110 D
b11111 E
b01010000000000001000000000000000 G
b00000000000000000000000000000001 H
#319
0C
#320
1C
b11111 D
b00000 E
b00000000000000000000000000000001 G
b01010000000000010100000000000000 H
#321
0C
#322
1C
b00000 D
b00001 E
b01010000000000010100000000000000 G
b00000000000000000000000000000001 H
#323
0C
#324
1C
b00001 D
b00010 E
b00000000000000000000000000000001 G
b01010000000000001101010011000011 H
#325
0C
b01010000000000001101010100100101 H
#326
1C
b00010 D
b00011 E
b01010000000000001101010101010001 G
b00000000000000000000000000000001 H
#327
0C
b01010000000000001101010110110011 G
#328
1C
b00011 D
b00100 E
b00000000000000000000000000000001 G
b00000000000000000010000000000000 H
#329
0C
#330
1C
b00100 D
b00101 E
b00000000000000000010000000000000 G
b00000000000000000000000000000000 H
#331
0C
#332
1C
b00101 D
b00110 E
b00000000000000000000000000000000 G
b00000000000000000000000001000000 H
#333
0C
#334
1C
b00110 D
b00111 E
b00000000000000000000000001000000 G
b00000000000000000000000000000000 H
#335
0C
#336
1C
b00111 D
b01000 E
b00000000000000000000000000000000 G
#337
0C
#338
1C
b01000 D
b01001 E
#339
0C
#340
1C
b01001 D
b01010 E
b01001000111000000100101101000000 H
#341
0C
#342
1C
b01010 D
b01011 E
b01001000111000000100101101000000 G
b00000000000000000000000000000001 H
#343
0C
#344
1C
b01011 D
b01100 E
b00000000000000000000000000000001 G
b01001000111000000100110101110000 H
#345
0C
#346
1C
b01100 D
b01101 E
b01001000111000000100110101110000 G
b00000000000000000000000000000001 H
#347
0C
#348
1C
b01101 D
b01110 E
b00000000000000000000000000000001 G
b01001000111000000100110101110000 H
#349
0C
#350
1C
b01110 D
b01111 E
b01001000111000000100110101110000 G
b00000000000000000000000000000001 H
#351
0C
#352
1C
b01111 D
b10000 E
b00000000000000000000000000000001 G
b00000000000000000000000000000000 H
#353
0C
#354
1C
b10000 D
b10001 E
b00000000000000000000000000000000 G
#355
0C
#356
1C
b10001 D
b10010 E
#357
0C
#358
1C
b10010 D
b10011 E
#359
0C
#360
1C
b10011 D
b10100 E
#361
0C
#362
1C
b10100 D
b10101 E
#363
0C
#364
1C
b10101 D
b10110 E
#365
0C
#366
1C
b10110 D
b10111 E
#367
0C
#368
1C
b10111 D
b11000 E
#369
0C
#370
1C
b11000 D
b11001 E
#371
0C
#372
1C
b11001 D
b11010 E
#373
0C
#374
1C
b11010 D
b11011 E
#375
0C
#376
1C
b11011 D
b11100 E
#377
0C
#378
1C
b11100 D
b11101 E
#379
0C
#380
1C
b11101 D
b11110 E
#381
0C
#382
1C
b11110 D
b11111 E
#383
0C
#384
1C
b11111 D
b00000 E
#385
0C
#386
1C
b00000 D
b00001 E
#387
0C
#388
1C
b00001 D
b00010 E
#389
0C
#390
1C
b00010 D
b00011 E
#391
0C
#392
1C
b00011 D
b00100 E
#393
0C
#394
1C
b00100 D
b00101 E
#395
0C
#396
1C
b00101 D
b00110 E
#397
0C
#398
1C
b00110 D
b00111 E
#399
0C
#400
1C
b00111 D
b01000 E
#401
0C
#402
1C
b01000 D
b01001 E
#403
0C
#404
1C
b01001 D
b01010 E
#405
0C
#406
1C
b01010 D
b01011 E
#407
0C
#408
1C
b01011 D
b01100 E
#409
0C
#410
1C
b01100 D
b01101 E
#411
0C
#412
1C
b01101 D
b01110 E
#413
0C
#414
1C
b01110 D
b01111 E
#415
0C
#416
1C
b01111 D
b10000 E
#417
0C
#418
1C
b10000 D
b10001 E
#419
0C
#420
1C
b10001 D
b10010 E
#421
0C
#422
1C
b10010 D
b10011 E
#423
0C
#424
1C
b10011 D
b10100 E
#425
0C
#426
1C
b10100 D
b10101 E
#427
0C
#428
1C
b10101 D
b10110 E
#429
0C
#430
1C
b10110 D
b10111 E
#431
0C
#432
1C
b10111 D
b11000 E
#433
0C
#434
1C
b11000 D
b11001 E
#435
0C
#436
1C
b11001 D
b11010 E
#437
0C
#438
1C
b11010 D
b11011 E
#439
0C
#440
1C
b11011 D
b11100 E
#441
0C
#442
1C
b11100 D
b11101 E
#443
0C
#444
1C
b11101 D
b11110 E
#445
0C
#446
1C
b11110 D
b11111 E
#447
0C
#448
1C
b11111 D
b00000 E
#449
0C
#450
1C
b00000 D
b00001 E
#451
0C
#452
1C
b00001 D
b00010 E
#453
0C
#454
1C
b00010 D
b00011 E
#455
0C
#456
1C
b00011 D
b00100 E
#457
0C
#458
1C
b00100 D
b00101 E
#459
0C
#460
1C
b00101 D
b00110 E
#461
0C
#462
1C
b00110 D
b00111 E
#463
0C
#464
1C
b00111 D
b01000 E
#465
0C
#466
1C
b01000 D
b01001 E
#467
0C
#468
1C
b01001 D
b01010 E
#469
0C
#470
1C
b01010 D
b01011 E
#471
0C
#472
1C
b01011 D
b01100 E
#473
0C
#474
1C
b01100 D
b01101 E
#475
0C
#476
1C
b01101 D
b01110 E
#477
0C
#478
1C
b01110 D
b01111 E
#479
0C
#480
1C
b01111 D
b10000 E
#481
0C
#482
1C
b10000 D
b10001 E
#483
0C
#484
1C
b10001 D
b10010 E
#485
0C
#486
1C
b10010 D
b10011 E
#487
0C
#488
1C
b10011 D
b10100 E
#489
0C
#490
1C
b10100 D
b10101 E
#491
0C
#492
1C
b10101 D
b10110 E
#493
0C
#494
1C
b10110 D
b10111 E
#495
0C
#496
1C
b10111 D
b11000 E
#497
0C
#498
1C
b11000 D
b11001 E
#499
0C
#500
1C
b11001 D
b11010 E
#501
0C
#502
1C
b11010 D
b11011 E
#503
0C
#504
1C
b11011 D
b11100 E
#505
0C
#506
1C
b11100 D
b11101 E
#507
0C
#508
1C
b11101 D
b11110 E
#509
0C
#510
1C
b11110 D
b11111 E
#511
0C
#512
1C
b11111 D
b00000 E
#513
0C
#514
1C
b00000 D
b00001 E
b00000000000000000000000000000001 H
#515
0C
#516
1C
b00001 D
b00010 E
b00000000000000000000000000000001 G
b00000000000000000000000000000010 H
#517
0C
#518
1C
b00010 D
b00011 E
b00000000000000000000000000000010 G
b00000000000000000000000000000011 H
#519
0C
#520
1C
b00011 D
b00100 E
b00000000000000000000000000000011 G
b00000000000000000000000000000100 H
#521
0C
#522
1C
b00100 D
b00101 E
b00000000000000000000000000000100 G
b00000000000000000000000000000101 H
#523
0C
#524
1C
b00101 D
b00110 E
b00000000000000000000000000000101 G
b00000000000000000000000000000110 H
#525
0C
#526
1C
b00110 D
b00111 E
b00000000000000000000000000000110 G
b00000000000000000000000000000111 H
#527
0C
#528
1C
b00111 D
b01000 E
b00000000000000000000000000000111 G
b00000000000000000000000000001000 H
#529
0C
#530
1C
b01000 D
b01001 E
b00000000000000000000000000001000 G
b00000000000000000000000000001001 H
#531
0C
#532
1C
b01001 D
b01010 E
b00000000000000000000000000001001 G
b00000000000000000000000000001010 H
#533
0C
#534
1C
b01010 D
b01011 E
b00000000000000000000000000001010 G
b00000000000000000000000000001011 H
#535
0C
#536
1C
b01011 D
b01100 E
b00000000000000000000000000001011 G
b00000000000000000000000000001100 H
#537
0C
#538
1C
b01100 D
b01101 E
b00000000000000000000000000001100 G
b00000000000000000000000000001101 H
#539
0C
#540
1C
b01101 D
b01110 E
b00000000000000000000000000001101 G
b00000000000000000000000000001110 H
#541
0C
#542
1C
b01110 D
b01111 E
b00000000000000000000000000001110 G
b00000000000000000000000000001111 H
#543
0C
#544
1C
b01111 D
b10000 E
b00000000000000000000000000001111 G
b00000000000000000000000000010000 H
#545
0C
