ProgramCounter.sv
module ProgramCounter 
(
    input logic clk,
    input logic rst,
    input logic [31:0] ImmOp,
    input logic PCsrc,
    output logic [31:0] PC
);

always_ff @(posedge clk)begin
    if(rst) 
        PC <= 0;
    else 
        if(PCsrc)
            PC <= PC + ImmOp;
        else
            PC <= PC + 4;
end

endmodule

ProgramCounter.vcd
$version Generated by VerilatedVcd $end
$date Fri Nov 18 11:38:53 2022 $end
$timescale 1ps $end

 $scope module TOP $end
  $var wire 32 % ImmOp [31:0] $end
  $var wire 32 ' PC [31:0] $end
  $var wire  1 & PCsrc $end
  $var wire  1 # clk $end
  $var wire  1 $ rst $end
  $scope module ProgramCounter $end
   $var wire 32 % ImmOp [31:0] $end
   $var wire 32 ' PC [31:0] $end
   $var wire  1 & PCsrc $end
   $var wire  1 # clk $end
   $var wire  1 $ rst $end
  $upscope $end
 $upscope $end
$enddefinitions $end


#0
1#
0$
b00000000000000000000000000000000 %
0&
b00000000000000000000000000000000 '
#1
0#
#2
1#
1$
b00000000000000000000000000000100 '
#3
0#
#4
1#
b00000000000000000000000000000000 '
#5
0#
#6
1#
0$
#7
0#
#8
1#
b00000000000000000000000000000100 '
#9
0#
#10
1#
b00000000000000000000000000001000 '
#11
0#
#12
1#
b00000000000000000000000000001100 '
#13
0#
#14
1#
b00000000000000000000000000010000 '
#15
0#
#16
1#
b00000000000000000000000000010100 '
#17
0#
#18
1#
b00000000000000000000000000011000 '
#19
0#
#20
1#
b00000000000000000000000000011100 '
#21
0#
#22
1#
b00000000000000000000000000000010 %
1&
b00000000000000000000000000100000 '
#23
0#
#24
1#
b00000000000000000000000000100010 '
#25
0#
#26
1#
b00000000000000000000000000100100 '
#27
0#
#28
1#
b00000000000000000000000000100110 '
#29
0#
#30
1#
b00000000000000000000000000101000 '
#31
0#
#32
1#
b00000000000000000000000000101010 '
#33
0#
#34
1#
b00000000000000000000000000101100 '
#35
0#
#36
1#
b00000000000000000000000000101110 '
#37
0#
#38
1#
b00000000000000000000000000110000 '
#39
0#
#40
1#
b00000000000000000000000000110010 '
#41
0#
#42
1#
b00000000000000000000000000110100 '
#43
0#
#44
1#
b00000000000000000000000000110110 '
#45
0#
#46
1#
b00000000000000000000000000111000 '
#47
0#
#48
1#
b00000000000000000000000000111010 '
#49
0#
#50
1#
b00000000000000000000000000111100 '
#51
0#
#52
1#
b00000000000000000000000000111110 '
#53
0#
#54
1#
b00000000000000000000000001000000 '
#55
0#
#56
1#
b00000000000000000000000001000010 '
#57
0#
#58
1#
b00000000000000000000000001000100 '
#59
0#
#60
1#
b00000000000000000000000001000110 '
#61
0#
#62
1#
b00000000000000000000000001001000 '
#63
0#
#64
1#
b00000000000000000000000001001010 '
#65
0#
#66
1#
b00000000000000000000000001001100 '
#67
0#
#68
1#
b00000000000000000000000001001110 '
#69
0#
#70
1#
b00000000000000000000000001010000 '
#71
0#
#72
1#
b00000000000000000000000001010010 '
#73
0#
#74
1#
b00000000000000000000000001010100 '
#75
0#
#76
1#
b00000000000000000000000001010110 '
#77
0#
#78
1#
b00000000000000000000000001011000 '
#79
0#
#80
1#
b00000000000000000000000001011010 '
#81
0#
#82
1#
b00000000000000000000000001011100 '
#83
0#
#84
1#
b00000000000000000000000001011110 '
#85
0#
#86
1#
b00000000000000000000000001100000 '
#87
0#
#88
1#
b00000000000000000000000001100010 '
#89
0#
#90
1#
b00000000000000000000000001100100 '
#91
0#
#92
1#
b00000000000000000000000001100110 '
#93
0#
#94
1#
b00000000000000000000000001101000 '
#95
0#
#96
1#
b00000000000000000000000001101010 '
#97
0#
#98
1#
b00000000000000000000000001101100 '
#99
0#
#100
1#
b00000000000000000000000001101110 '
#101
0#
#102
1#
b00000000000000000000000001110000 '
#103
0#
#104
1#
b00000000000000000000000001110010 '
#105
0#
#106
1#
b00000000000000000000000001110100 '
#107
0#
#108
1#
b00000000000000000000000001110110 '
#109
0#
#110
1#
b00000000000000000000000001111000 '
#111
0#
#112
1#
b00000000000000000000000001111010 '
#113
0#
#114
1#
b00000000000000000000000001111100 '
#115
0#
#116
1#
b00000000000000000000000001111110 '
#117
0#
#118
1#
b00000000000000000000000010000000 '
#119
0#
#120
1#
b00000000000000000000000010000010 '
#121
0#
#122
1#
b00000000000000000000000010000100 '
#123
0#
#124
1#
b00000000000000000000000010000110 '
#125
0#
#126
1#
b00000000000000000000000010001000 '
#127
0#
#128
1#
b00000000000000000000000010001010 '
#129
0#
#130
1#
b00000000000000000000000010001100 '
#131
0#
#132
1#
b00000000000000000000000010001110 '
#133
0#
#134
1#
b00000000000000000000000010010000 '
#135
0#
#136
1#
b00000000000000000000000010010010 '
#137
0#
#138
1#
b00000000000000000000000010010100 '
#139
0#
#140
1#
b00000000000000000000000010010110 '
#141
0#
#142
1#
b00000000000000000000000010011000 '
#143
0#
#144
1#
b00000000000000000000000010011010 '
#145
0#
#146
1#
b00000000000000000000000010011100 '
#147
0#
#148
1#
b00000000000000000000000010011110 '
#149
0#
#150
1#
b00000000000000000000000010100000 '
#151
0#
#152
1#
b00000000000000000000000010100010 '
#153
0#
#154
1#
b00000000000000000000000010100100 '
#155
0#
#156
1#
b00000000000000000000000010100110 '
#157
0#
#158
1#
b00000000000000000000000010101000 '
#159
0#
#160
1#
b00000000000000000000000010101010 '
#161
0#
#162
1#
b00000000000000000000000010101100 '
#163
0#
#164
1#
b00000000000000000000000010101110 '
#165
0#
#166
1#
b00000000000000000000000010110000 '
#167
0#
#168
1#
b00000000000000000000000010110010 '
#169
0#
#170
1#
b00000000000000000000000010110100 '
#171
0#
#172
1#
b00000000000000000000000010110110 '
#173
0#
#174
1#
b00000000000000000000000010111000 '
#175
0#
#176
1#
b00000000000000000000000010111010 '
#177
0#
#178
1#
b00000000000000000000000010111100 '
#179
0#
#180
1#
b00000000000000000000000010111110 '
#181
0#
#182
1#
b00000000000000000000000011000000 '
#183
0#
#184
1#
b00000000000000000000000011000010 '
#185
0#
#186
1#
b00000000000000000000000011000100 '
#187
0#
#188
1#
b00000000000000000000000011000110 '
#189
0#
#190
1#
b00000000000000000000000011001000 '
#191
0#
#192
1#
b00000000000000000000000011001010 '
#193
0#
#194
1#
b00000000000000000000000011001100 '
#195
0#
#196
1#
b00000000000000000000000011001110 '
#197
0#
#198
1#
b00000000000000000000000011010000 '
