pipelined/mux_2.sv
module mux_2 #(
    parameter VALUE_WIDTH = 32
)(
    input  logic                  sel,
    input  logic[VALUE_WIDTH-1:0] in0,
    input  logic[VALUE_WIDTH-1:0] in1,
    output logic[VALUE_WIDTH-1:0] out
);

assign out = sel ? in1 : in0;

endmodule

f1_cpu/ram.sv
module ram #(
    parameter ADDR_WIDTH = 12,
              DATA_WIDTH = 8
)(
    input  logic[ADDR_WIDTH-1:0] read_addr,
    input  logic[ADDR_WIDTH-1:0] write_addr,
    input  logic[31:0]           din,
    output logic[31:0]           dout,
    input  logic                 write_en,
    input  logic                 clk
);

bit[DATA_WIDTH-1:0] memory[2**DATA_WIDTH-1:0];

always_comb begin
    dout = {memory[read_addr+3], memory[read_addr+2], memory[read_addr+1], memory[read_addr]};
end

always_ff @(posedge clk) begin
    if (write_en) begin
        memory[write_addr] <= din[7:0];
        memory[write_addr+1] <= din[15:8];
        memory[write_addr+2] <= din[23:16];
        memory[write_addr+3] <= din[31:24];
    end
end

endmodule

alu/alu.sv
module alu #(
    parameter DATA_WIDTH = 32
)(
    input  logic[2:0]            ctrl,
    input  logic[DATA_WIDTH-1:0] op1, op2,
    output logic[DATA_WIDTH-1:0] out,
    output logic                 zero, less_than_unsigned, less_than_signed
);

always_comb begin
    case(ctrl)
        0: out = op1 + op2;
        1: out = op1 - op2;
        2: out = op1 & op2;
        3: out = op1 | op2;
        4: out = op1 ^ op2;
        5: out = op1 << op2;
        6: out = op1 >> op2;
        default: out = 0;
    endcase
end

always_comb begin
    zero = (out == 0);
    unsigned_less_than = (unsigned'(op1) < unsigned'(op2));
    signed_less_than = (signed'(op1) < signed'(op2));
end

endmodule

f1_cpu/adder.sv
module adder(
    input [31:0] i1,
    input [31:0] i2,
    output [31:0] out
);

assign out = i1 + i2;

endmodule

f1_cpu/program_counter.sv
module program_counter 
(
    input logic clk,
    input logic rst,
    input logic [31:0] ImmOp,
    input logic PCsrc,
    output logic [31:0] PC
);

always_ff @(posedge clk) begin
    if(rst) 
        PC <= 0;
    else 
        if(PCsrc)
            PC <= PC + ImmOp;
        else
            PC <= PC + 4;
end


endmodule

f1_cpu/instr_rom.sv
module instr_rom #(
    parameter ADDR_WIDTH = 16,
              DATA_WIDTH = 32
)(
    input  logic[ADDR_WIDTH-1:0] addr,
    output logic[DATA_WIDTH-1:0] dout
);

logic[DATA_WIDTH-1:0] memory[2**ADDR_WIDTH-1:0];

initial begin
    $readmemh("f1.s.hex", memory);
end

assign dout = memory[addr];
    
endmodule

f1_cpu/sign_extend.sv
module sign_extend (
    input logic[31:7] immediate,
    input logic [1:0] ImmSrc,
    output logic [31:0] ImmExt
);

always_comb begin
    case (ImmSrc)
        0: ImmExt = {{21{immediate[31]}}, immediate[30:20]};
        1: ImmExt = {{20{immediate[31]}}, immediate[7], immediate[30:25], immediate[11:8],1'b0};
        2: ImmExt = {immediate[31], immediate[30:12], 12'b0};
        3: ImmExt = {{12{immediate[31]}}, immediate[19:12], immediate[20], immediate[30:21], 1'b0};
    endcase
end



endmodule

single_cycle/register_file.sv
module register_file #(
    parameter ADDR_WIDTH = 5,
              DATA_WIDTH = 32
)(
    input  logic                 clk,
    input  logic[ADDR_WIDTH-1:0] ad1,
    input  logic[ADDR_WIDTH-1:0] ad2,
    input  logic[ADDR_WIDTH-1:0] ad3,
    output logic[DATA_WIDTH-1:0] rd1,
    output logic[DATA_WIDTH-1:0] rd2,
    input  logic[DATA_WIDTH-1:0] wd3,
    input  logic                 we3,
    output logic[DATA_WIDTH-1:0] a0
);
    
logic[DATA_WIDTH-1:0] registers[2**ADDR_WIDTH-1:0];

always_comb begin
    rd1 = (ad1 == 0) ? 0 : registers[ad1]; // x0 is the constant zero register
    rd2 = (ad2 == 0) ? 0 : registers[ad2];
    a0 = registers[10];                    // a0 is register x10
end

always_ff @(posedge clk) begin
    if(we3) registers[ad3] <= wd3;
end

endmodule

f1_cpu/control.sv
module control (
    // interface signals
    input logic [6:0] op,
    input logic [2:0] func3,
    input logic func7_5,
    input logic Zero,
    output logic RegWrite, //clk
    output logic [2:0] ALUctrl, //add,addi = 0; sub = 1; and,andi = 2; or = 3; xori = 4; slli = 5; srli = 6; default = 0; 7 for nothing
    output logic ALUsrcB, // enable
    output logic [1:0] ImmSrc,//I = 0; B = 1; U = 2; J = 3 (R-type not included, default 0)
    output logic PCsrc, //count output
    output logic ResultSrc, // only 1 if load
    output logic MemWrite,
    output logic ALUsrcA, // only 1 for auipc, 0 otherwise
    output logic JALctrl // 1 if jalr or jal, 0 otherwise
);
// indicates that this is a clocked circuit

always_comb begin
    if(op==19) begin
        assign JALctrl = 0;
        assign ALUsrcB = 1; //immediate
        assign ImmSrc = 0; //I-type
        assign RegWrite = 1; // alu
        assign ResultSrc = 0;
        assign PCsrc = 0;
        assign MemWrite = 0;
        assign ALUsrcA = 0;
        if (func3==0) begin //addi
            assign ALUctrl = 0;
        end
        else if (func3==1) begin //slli
            assign ALUctrl = 5;
        end
        else if (func3==4) begin //xori
            assign ALUctrl = 4;
        end
        else if (func3==5) begin //srli
            assign ALUctrl = 6;
        end
        else if (func3==7) begin //andi
            assign ALUctrl = 2;
        end
    end 

    else if(op==23) begin //auipc
        assign JALctrl = 0;
        assign PCsrc = 0;
        assign ALUsrcB = 1;
        assign ImmSrc = 2;
        assign RegWrite = 1;
        assign ResultSrc = 0;
        assign MemWrite = 0;
        assign ALUctrl = 0; //add upper immediate
        assign ALUsrcA = 1;
    end

    else if(op==35) begin// store
        assign JALctrl = 0;
        assign MemWrite = 1;
        assign ResultSrc = 0; 
        assign PCsrc = 0;
        assign ALUsrcB = 0;
        assign ImmSrc = 0;
        assign RegWrite = 0;
        assign ALUctrl = 7;
        assign ALUsrcA = 0;
    end

    else if(op==51) begin
        assign JALctrl = 0;
        assign ALUsrcB = 0; // RD2
        assign ImmSrc = 0; //R-type
        assign RegWrite = 1; // alu
        assign ResultSrc = 0;
        assign PCsrc = 0;
        assign MemWrite = 0;
        assign ALUsrcA = 0;
        if (func3==0 && func7_5==0) begin //add
            assign ALUctrl = 0;
        end
        if (func3==0 && func7_5==1) begin //sub
            assign ALUctrl = 1;
        end
        else if (func3==6) begin //or
            assign ALUctrl = 3;
        end
        else if (func3==7) begin //and
            assign ALUctrl = 2;
        end
    end

    else if(op==55) begin // lui
        assign JALctrl = 0;
        assign ImmSrc = 2;
        assign RegWrite = 1;
        assign ALUsrcB = 1;
        assign PCsrc = 0;
        assign ResultSrc = 0;
        assign MemWrite = 0;
        assign ALUctrl = 7;
        assign ALUsrcA = 0;
    end

    else if(op==99) begin
        assign JALctrl = 0;
        assign ALUctrl = 1; // bne, beq need minus
        if (func3==0) // beq
            PCsrc = Zero;
        else if (func3==1) //bne
            PCsrc = !Zero;
        assign ResultSrc = 0;
        assign MemWrite = 0;
        assign ALUsrcB = 0;
        assign ImmSrc = 1;
        assign RegWrite = 0;
        assign ALUsrcA = 0;
    end


    else if(op==103) begin //jalr
        assign JALctrl = 1;
        assign ImmSrc = 0;
        assign PCsrc = 1;
        assign ALUsrcB = 1;
        assign RegWrite = 1;
        assign MemWrite = 0;
        assign ResultSrc = 0;
        assign ALUctrl = 7;
        assign ALUsrcA = 1;
    end

    else if(op==111) begin // jal
        assign JALctrl = 1;
        assign PCsrc = 1;
        assign ResultSrc = 0;
        assign MemWrite = 0;
        assign ALUctrl = 7;
        assign ALUsrcB = 0;
        assign ImmSrc = 3;
        assign RegWrite = 1;
        assign ALUsrcA = 1;
    end

    else if(op==3) begin //load
        assign JALctrl = 0;
        assign PCsrc = 0;
        assign ResultSrc = 1;
        assign MemWrite = 0;
        assign ALUctrl = 7;
        assign ALUsrcB = 0;
        assign ImmSrc = 0;
        assign RegWrite = 1;
        assign ALUsrcA = 0;
    end
        

    

end





endmodule

f1_cpu/f1_cpu.sv
module f1_cpu #(
    parameter ADDR_WIDTH = 16,
              DATA_WIDTH = 32
)(
   input logic clk,
   input logic rst,
   output logic a0

);
 logic [ADDR_WIDTH-1:0] PC;
 logic [DATA_WIDTH-1:0] instr;
 logic PCSrc;
 logic ResultSrc;
 logic [2:0] ALUctrl;
 logic ALUSrcB;
 logic [1:0] ImmSrc;
 logic RegWrite;
 logic Zero;
 logic MemWrite;
 logic ALUSrcA;
 logic JALctrl;
 logic [DATA_WIDTH-1:0] rd1;
 logic [DATA_WIDTH-1:0] rd2;
 logic [DATA_WIDTH-1:0] Result;
 logic [DATA_WIDTH-1:0] ImmExt;
 logic [DATA_WIDTH-1:0] PCTarget;
 logic [DATA_WIDTH-1:0] JALResult;
 logic [DATA_WIDTH-1:0] SrcA;
 logic [DATA_WIDTH-1:0] SrcB;
 logic [DATA_WIDTH-1:0] ReadData;

 control Control_Unit(
     .op(instr[6:0]),
     .func3(instr[14:12]),
     .func7_5(instr[30]),
     .Zero(Zero),
     .RegWrite(RegWrite),
     .ALUctrl(ALUctrl),
     .ALUsrcB(ALUSrcB),
     .ImmSrc(ImmSrc),
     .PCsrc(PCsrc),
     .ResultSrc(ResultSrc),
     .MemWrite(MemWrite),
     .ALUsrcA(ALUSrcA),
     .JALctrl(JALctrl)
 );

 register_file MyRegister(
     .clk(clk),
     .ad1(instr[19:15]),
     .ad2(instr[24:20]),
     .ad3(instr[11:7]),
     .rd1(rd1),
     .rd2(rd2),
     .wd3(JALResult),
     .we3(RegWrite),
     .a0(a0)
 );

 sign_extend Extend(
     .immediate(instr[31:7]),
     .ImmSrc(ImmSrc),
     .ImmExt(ImmExt)
 );

 instr_rom Instr_Mem(
     .addr(PC),
     .dout(instr)
 );

 program_counter Program_Counter(
     .clk(clk),
     .rst(rst),
     .ImmOp(PCTarget),
     .PCsrc(PCsrc),
     .PC(PC)
 );

 adder PCTargetAdder(
     .i1(PC),
     .i2(ImmExt),
     .out(PCTarget)
 );

 mux_2 JAL_mux(
     .sel(JALctrl),
     .in0(Result),
     .in1(PC+4),
     .out(JALResult)
 );

 mux_2 ALU_mux_A(
     .sel(ALUSrcA),
     .in0(rd1),
     .in1(PC),
     .out(SrcA)
 );

 mux_2 ALU_mux_B(
     .sel(ALUSrcB),
     .in0(rd2),
     .in1(ImmExt),
     .out(SrcB)
 );

 alu MyALU(
     .ctrl(ALUctrl),
     .op1(SrcA),
     .op2(SrcB),
     .out(ALUResult),
     .zero(Zero)
 );

 ram Data_Mem(
     .read_addr(ALUResult),
     .write_addr(ALUResult),
     .din(rd2),
     .dout(ReadData),
     .write_en(MemWrite),
     .clk(clk)
 );

 mux_2 Result_Mux(
     .sel(ResultSrc),
     .in0(ALUResult),
     .in1(ReadData),
     .out(Result)
 );

endmodule

f1_cpu/f1_cpu.vcd
$version Generated by VerilatedVcd $end
$date Fri Dec  9 11:55:04 2022 $end
$timescale 1ps $end

 $scope module TOP $end
  $var wire  1 k a0 $end
  $var wire  1 i clk $end
  $var wire  1 j rst $end
  $scope module f1_cpu $end
   $var wire 32 l ADDR_WIDTH [31:0] $end
   $var wire  1 8 ALUResult $end
   $var wire  1 , ALUSrcA $end
   $var wire  1 ' ALUSrcB $end
   $var wire  3 & ALUctrl [2:0] $end
   $var wire 32 m DATA_WIDTH [31:0] $end
   $var wire 32 1 ImmExt [31:0] $end
   $var wire  2 ( ImmSrc [1:0] $end
   $var wire 32 3 JALResult [31:0] $end
   $var wire  1 - JALctrl $end
   $var wire  1 + MemWrite $end
   $var wire 16 # PC [15:0] $end
   $var wire  1 n PCSrc $end
   $var wire 32 2 PCTarget [31:0] $end
   $var wire  1 7 PCsrc $end
   $var wire 32 6 ReadData [31:0] $end
   $var wire  1 ) RegWrite $end
   $var wire 32 0 Result [31:0] $end
   $var wire  1 % ResultSrc $end
   $var wire 32 4 SrcA [31:0] $end
   $var wire 32 5 SrcB [31:0] $end
   $var wire  1 * Zero $end
   $var wire  1 k a0 $end
   $var wire  1 i clk $end
   $var wire 32 $ instr [31:0] $end
   $var wire 32 . rd1 [31:0] $end
   $var wire 32 / rd2 [31:0] $end
   $var wire  1 j rst $end
   $scope module ALU_mux_A $end
    $var wire 32 m VALUE_WIDTH [31:0] $end
    $var wire 32 . in0 [31:0] $end
    $var wire 32 9 in1 [31:0] $end
    $var wire 32 4 out [31:0] $end
    $var wire  1 , sel $end
   $upscope $end
   $scope module ALU_mux_B $end
    $var wire 32 m VALUE_WIDTH [31:0] $end
    $var wire 32 / in0 [31:0] $end
    $var wire 32 1 in1 [31:0] $end
    $var wire 32 5 out [31:0] $end
    $var wire  1 ' sel $end
   $upscope $end
   $scope module Control_Unit $end
    $var wire  3 & ALUctrl [2:0] $end
    $var wire  1 , ALUsrcA $end
    $var wire  1 ' ALUsrcB $end
    $var wire  2 ( ImmSrc [1:0] $end
    $var wire  1 - JALctrl $end
    $var wire  1 + MemWrite $end
    $var wire  1 7 PCsrc $end
    $var wire  1 ) RegWrite $end
    $var wire  1 % ResultSrc $end
    $var wire  1 * Zero $end
    $var wire  3 ; func3 [2:0] $end
    $var wire  1 < func7_5 $end
    $var wire  7 : op [6:0] $end
   $upscope $end
   $scope module Data_Mem $end
    $var wire 32 o ADDR_WIDTH [31:0] $end
    $var wire 32 p DATA_WIDTH [31:0] $end
    $var wire  1 i clk $end
    $var wire 32 / din [31:0] $end
    $var wire 32 6 dout [31:0] $end
    $var wire 12 = read_addr [11:0] $end
    $var wire 12 = write_addr [11:0] $end
    $var wire  1 + write_en $end
   $upscope $end
   $scope module Extend $end
    $var wire 32 1 ImmExt [31:0] $end
    $var wire  2 ( ImmSrc [1:0] $end
    $var wire 25 > immediate [31:7] $end
   $upscope $end
   $scope module Instr_Mem $end
    $var wire 32 l ADDR_WIDTH [31:0] $end
    $var wire 32 m DATA_WIDTH [31:0] $end
    $var wire 16 # addr [15:0] $end
    $var wire 32 $ dout [31:0] $end
   $upscope $end
   $scope module JAL_mux $end
    $var wire 32 m VALUE_WIDTH [31:0] $end
    $var wire 32 0 in0 [31:0] $end
    $var wire 32 ? in1 [31:0] $end
    $var wire 32 3 out [31:0] $end
    $var wire  1 - sel $end
   $upscope $end
   $scope module MyALU $end
    $var wire 32 m DATA_WIDTH [31:0] $end
    $var wire  3 & ctrl [2:0] $end
    $var wire  1 B less_than_signed $end
    $var wire  1 A less_than_unsigned $end
    $var wire 32 4 op1 [31:0] $end
    $var wire 32 5 op2 [31:0] $end
    $var wire 32 @ out [31:0] $end
    $var wire  1 * zero $end
   $upscope $end
   $scope module MyRegister $end
    $var wire 32 q ADDR_WIDTH [31:0] $end
    $var wire 32 m DATA_WIDTH [31:0] $end
    $var wire 32 F a0 [31:0] $end
    $var wire  5 C ad1 [4:0] $end
    $var wire  5 D ad2 [4:0] $end
    $var wire  5 E ad3 [4:0] $end
    $var wire  1 i clk $end
    $var wire 32 . rd1 [31:0] $end
    $var wire 32 / rd2 [31:0] $end
    $var wire 32 G registers[0] [31:0] $end
    $var wire 32 Q registers[10] [31:0] $end
    $var wire 32 R registers[11] [31:0] $end
    $var wire 32 S registers[12] [31:0] $end
    $var wire 32 T registers[13] [31:0] $end
    $var wire 32 U registers[14] [31:0] $end
    $var wire 32 V registers[15] [31:0] $end
    $var wire 32 W registers[16] [31:0] $end
    $var wire 32 X registers[17] [31:0] $end
    $var wire 32 Y registers[18] [31:0] $end
    $var wire 32 Z registers[19] [31:0] $end
    $var wire 32 H registers[1] [31:0] $end
    $var wire 32 [ registers[20] [31:0] $end
    $var wire 32 \ registers[21] [31:0] $end
    $var wire 32 ] registers[22] [31:0] $end
    $var wire 32 ^ registers[23] [31:0] $end
    $var wire 32 _ registers[24] [31:0] $end
    $var wire 32 ` registers[25] [31:0] $end
    $var wire 32 a registers[26] [31:0] $end
    $var wire 32 b registers[27] [31:0] $end
    $var wire 32 c registers[28] [31:0] $end
    $var wire 32 d registers[29] [31:0] $end
    $var wire 32 I registers[2] [31:0] $end
    $var wire 32 e registers[30] [31:0] $end
    $var wire 32 f registers[31] [31:0] $end
    $var wire 32 J registers[3] [31:0] $end
    $var wire 32 K registers[4] [31:0] $end
    $var wire 32 L registers[5] [31:0] $end
    $var wire 32 M registers[6] [31:0] $end
    $var wire 32 N registers[7] [31:0] $end
    $var wire 32 O registers[8] [31:0] $end
    $var wire 32 P registers[9] [31:0] $end
    $var wire 32 3 wd3 [31:0] $end
    $var wire  1 ) we3 $end
   $upscope $end
   $scope module PCTargetAdder $end
    $var wire 32 9 i1 [31:0] $end
    $var wire 32 1 i2 [31:0] $end
    $var wire 32 2 out [31:0] $end
   $upscope $end
   $scope module Program_Counter $end
    $var wire 32 2 ImmOp [31:0] $end
    $var wire 32 g PC [31:0] $end
    $var wire  1 7 PCsrc $end
    $var wire  1 i clk $end
    $var wire  1 j rst $end
   $upscope $end
   $scope module Result_Mux $end
    $var wire 32 m VALUE_WIDTH [31:0] $end
    $var wire 32 h in0 [31:0] $end
    $var wire 32 6 in1 [31:0] $end
    $var wire 32 0 out [31:0] $end
    $var wire  1 % sel $end
   $upscope $end
  $upscope $end
 $upscope $end
$enddefinitions $end


#0
b0000000000000000 #
b00000000000000000000000000010011 $
0%
b000 &
1'
b00 (
1)
1*
0+
0,
0-
b00000000000000000000000000000000 .
b00000000000000000000000000000000 /
b00000000000000000000000000000000 0
b00000000000000000000000000000000 1
b00000000000000000000000000000000 2
b00000000000000000000000000000000 3
b00000000000000000000000000000000 4
b00000000000000000000000000000000 5
b00000000000000000000000000000000 6
07
08
b00000000000000000000000000000000 9
b0010011 :
b000 ;
0<
b000000000000 =
b0000000000000000000000000 >
b00000000000000000000000000000100 ?
b00000000000000000000000000000000 @
0A
0B
b00000 C
b00000 D
b00000 E
b00000000000000000000000000000000 F
b00000000000000000000000000000000 G
b00000000000000000000000000000000 H
b00000000000000000000000000000000 I
b00000000000000000000000000000000 J
b00000000000000000000000000000000 K
b00000000000000000000000000000000 L
b00000000000000000000000000000000 M
b00000000000000000000000000000000 N
b00000000000000000000000000000000 O
b00000000000000000000000000000000 P
b00000000000000000000000000000000 Q
b00000000000000000000000000000000 R
b00000000000000000000000000000000 S
b00000000000000000000000000000000 T
b00000000000000000000000000000000 U
b00000000000000000000000000000000 V
b00000000000000000000000000000000 W
b00000000000000000000000000000000 X
b00000000000000000000000000000000 Y
b00000000000000000000000000000000 Z
b00000000000000000000000000000000 [
b00000000000000000000000000000000 \
b00000000000000000000000000000000 ]
b00000000000000000000000000000000 ^
b00000000000000000000000000000000 _
b00000000000000000000000000000000 `
b00000000000000000000000000000000 a
b00000000000000000000000000000000 b
b00000000000000000000000000000000 c
b00000000000000000000000000000000 d
b00000000000000000000000000000000 e
b00000000000000000000000000000000 f
b00000000000000000000000000000000 g
b00000000000000000000000000000000 h
0i
0j
0k
b00000000000000000000000000010000 l
b00000000000000000000000000100000 m
0n
b00000000000000000000000000001100 o
b00000000000000000000000000001000 p
b00000000000000000000000000000101 q
#1
b0000000000000100 #
b00000000000000000000000000000100 2
b00000000000000000000000000000100 9
b00000000000000000000000000001000 ?
b00000000000000000000000000000100 g
1i
#2
0i
#3
b0000000000001000 #
b00000000000000000000000010010011 $
b00000000000000000000000000001000 2
b00000000000000000000000000001000 9
b0000000000000000000000001 >
b00000000000000000000000000001100 ?
b00001 E
b00000000000000000000000000001000 g
1i
#4
0i
#5
b0000000000001100 #
b00000000000000000000000000010011 $
b00000000000000000000000000001100 2
b00000000000000000000000000001100 9
b0000000000000000000000000 >
b00000000000000000000000000010000 ?
b00000 E
b00000000000000000000000000001100 g
1i
#6
0i
#7
b0000000000010000 #
b00000000000000000000000000010000 2
b00000000000000000000000000010000 9
b00000000000000000000000000010100 ?
b00000000000000000000000000010000 g
1i
#8
0i
#9
b0000000000010100 #
b00000000000000000000000000010100 2
b00000000000000000000000000010100 9
b00000000000000000000000000011000 ?
b00000000000000000000000000010100 g
1i
#10
0i
#11
b0000000000011000 #
b00000000000000000000000011101111 $
b111 &
0'
b11 (
0*
1,
1-
b00000000000000000000000000011000 2
b00000000000000000000000000011100 3
b00000000000000000000000000011000 4
17
b00000000000000000000000000011000 9
b1101111 :
b0000000000000000000000001 >
b00000000000000000000000000011100 ?
b00000000000000000000000000011000 @
b00001 E
b00000000000000000000000000011000 g
1i
#12
0i
#13
b0000000000110000 #
b00000000000000000000000000010011 $
b000 &
1'
b00 (
1*
0,
0-
b00000000000000000000000000110000 2
b00000000000000000000000000000000 3
b00000000000000000000000000000000 4
07
b00000000000000000000000000110000 9
b0010011 :
b0000000000000000000000000 >
b00000000000000000000000000110100 ?
b00000000000000000000000000000000 @
b00000 E
b00000000000000000000000000011100 H
b00000000000000000000000000110000 g
1i
#14
0i
#15
b0000000000110100 #
b00000000000000000000000011101111 $
b111 &
0'
b11 (
0*
1,
1-
b00000000000000000000000000110100 2
b00000000000000000000000000111000 3
b00000000000000000000000000110100 4
17
b00000000000000000000000000110100 9
b1101111 :
b0000000000000000000000001 >
b00000000000000000000000000111000 ?
b00000000000000000000000000110100 @
b00001 E
b00000000000000000000000000110100 g
1i
#16
0i
#17
b0000000001101000 #
b00000000000000000000000010010011 $
b000 &
1'
b00 (
1*
0,
0-
b00000000000000000000000001101000 2
b00000000000000000000000000000000 3
b00000000000000000000000000000000 4
07
b00000000000000000000000001101000 9
b0010011 :
b00000000000000000000000001101100 ?
b00000000000000000000000000000000 @
b00000000000000000000000000111000 H
b00000000000000000000000001101000 g
1i
#18
0i
#19
b0000000001101100 #
b00000000000000000000000010110011 $
0'
b00000000000000000000000001101100 2
b00000000000000000000000001101100 9
b0110011 :
b00000000000000000000000001110000 ?
b00000000000000000000000000000000 H
b00000000000000000000000001101100 g
1i
#20
0i
#21
b0000000001110000 #
b00000000000000000000000010010011 $
1'
b00000000000000000000000001110000 2
b00000000000000000000000001110000 9
b0010011 :
b00000000000000000000000001110100 ?
b00000000000000000000000001110000 g
1i
#22
0i
#23
b0000000001110100 #
b00000000000000000000000010110011 $
0'
b00000000000000000000000001110100 2
b00000000000000000000000001110100 9
b0110011 :
b00000000000000000000000001111000 ?
b00000000000000000000000001110100 g
1i
#24
0i
#25
b0000000001111000 #
b00000000000000000000000000010011 $
1'
b00000000000000000000000001111000 2
b00000000000000000000000001111000 9
b0010011 :
b0000000000000000000000000 >
b00000000000000000000000001111100 ?
b00000 E
b00000000000000000000000001111000 g
1i
#26
0i
#27
b0000000001111100 #
b00000000000000000000000001111100 2
b00000000000000000000000001111100 9
b00000000000000000000000010000000 ?
b00000000000000000000000001111100 g
1i
#28
0i
#29
b0000000010000000 #
b00000000000000000000000010000000 2
b00000000000000000000000010000000 9
b00000000000000000000000010000100 ?
b00000000000000000000000010000000 g
1i
#30
0i
#31
b0000000010000100 #
b00000000000000000000000000110011 $
0'
b00000000000000000000000010000100 2
b00000000000000000000000010000100 9
b0110011 :
b00000000000000000000000010001000 ?
b00000000000000000000000010000100 g
1i
#32
0i
#33
b0000000010001000 #
b00000000000000000000000010010011 $
1'
b00000000000000000000000010001000 2
b00000000000000000000000010001000 9
b0010011 :
b0000000000000000000000001 >
b00000000000000000000000010001100 ?
b00001 E
b00000000000000000000000010001000 g
1i
#34
0i
#35
b0000000010001100 #
b00000000000000000000000001100111 $
b111 &
0*
1,
1-
b00000000000000000000000010001100 2
b00000000000000000000000010010000 3
b00000000000000000000000010001100 4
17
b00000000000000000000000010001100 9
b1100111 :
b0000000000000000000000000 >
b00000000000000000000000010010000 ?
b00000000000000000000000010001100 @
b00000 E
b00000000000000000000000010001100 g
1i
#36
0i
#37
b0000000100011000 #
b00000000000000000000000000000000 $
b00000000000000000000000100011000 2
b00000000000000000000000100011100 3
b00000000000000000000000100011000 4
b00000000000000000000000100011000 9
b0000000 :
b00000000000000000000000100011100 ?
b00000000000000000000000100011000 @
b00000000000000000000000010010000 G
b00000000000000000000000100011000 g
1i
#38
0i
#39
b0000001000110000 #
b00000000000000000000001000110000 2
b00000000000000000000001000110100 3
b00000000000000000000001000110000 4
b00000000000000000000001000110000 9
b00000000000000000000001000110100 ?
b00000000000000000000001000110000 @
b00000000000000000000000100011100 G
b00000000000000000000001000110000 g
1i
#40
0i
#41
b0000010001100000 #
b00000000000000000000010001100000 2
b00000000000000000000010001100100 3
b00000000000000000000010001100000 4
b00000000000000000000010001100000 9
b00000000000000000000010001100100 ?
b00000000000000000000010001100000 @
b00000000000000000000001000110100 G
b00000000000000000000010001100000 g
1i
#42
0i
#43
b0000100011000000 #
b00000000000000000000100011000000 2
b00000000000000000000100011000100 3
b00000000000000000000100011000000 4
b00000000000000000000100011000000 9
b00000000000000000000100011000100 ?
b00000000000000000000100011000000 @
b00000000000000000000010001100100 G
b00000000000000000000100011000000 g
1i
#44
0i
#45
b0001000110000000 #
b00000000000000000001000110000000 2
b00000000000000000001000110000100 3
b00000000000000000001000110000000 4
b00000000000000000001000110000000 9
b00000000000000000001000110000100 ?
b00000000000000000001000110000000 @
b00000000000000000000100011000100 G
b00000000000000000001000110000000 g
1i
#46
0i
#47
b0010001100000000 #
b00000000000000000010001100000000 2
b00000000000000000010001100000100 3
b00000000000000000010001100000000 4
b00000000000000000010001100000000 9
b00000000000000000010001100000100 ?
b00000000000000000010001100000000 @
b00000000000000000001000110000100 G
b00000000000000000010001100000000 g
1i
#48
0i
#49
b0100011000000000 #
b00000000000000000100011000000000 2
b00000000000000000100011000000100 3
b00000000000000000100011000000000 4
b00000000000000000100011000000000 9
b00000000000000000100011000000100 ?
b00000000000000000100011000000000 @
b00000000000000000010001100000100 G
b00000000000000000100011000000000 g
1i
#50
0i
#51
b1000110000000000 #
b00000000000000001000110000000000 2
b00000000000000001000110000000100 3
b00000000000000001000110000000000 4
b00000000000000001000110000000000 9
b00000000000000001000110000000100 ?
b00000000000000001000110000000000 @
b00000000000000000100011000000100 G
b00000000000000001000110000000000 g
1i
#52
0i
#53
b0001100000000000 #
b00000000000000000001100000000000 2
b00000000000000000001100000000100 3
b00000000000000000001100000000000 4
b00000000000000000001100000000000 9
b00000000000000000001100000000100 ?
b00000000000000000001100000000000 @
b00000000000000001000110000000100 G
b00000000000000010001100000000000 g
1i
#54
0i
#55
b0011000000000000 #
b00000000000000000011000000000000 2
b00000000000000000011000000000100 3
b00000000000000000011000000000000 4
b00000000000000000011000000000000 9
b00000000000000000011000000000100 ?
b00000000000000000011000000000000 @
b00000000000000000001100000000100 G
b00000000000000010011000000000000 g
1i
#56
0i
#57
b0110000000000000 #
b00000000000000000110000000000000 2
b00000000000000000110000000000100 3
b00000000000000000110000000000000 4
b00000000000000000110000000000000 9
b00000000000000000110000000000100 ?
b00000000000000000110000000000000 @
b00000000000000000011000000000100 G
b00000000000000010110000000000000 g
1i
#58
0i
#59
b1100000000000000 #
b00000000000000001100000000000000 2
b00000000000000001100000000000100 3
b00000000000000001100000000000000 4
b00000000000000001100000000000000 9
b00000000000000001100000000000100 ?
b00000000000000001100000000000000 @
b00000000000000000110000000000100 G
b00000000000000011100000000000000 g
1i
#60
0i
#61
b1000000000000000 #
b00000000000000001000000000000000 2
b00000000000000001000000000000100 3
b00000000000000001000000000000000 4
b00000000000000001000000000000000 9
b00000000000000001000000000000100 ?
b00000000000000001000000000000000 @
b00000000000000001100000000000100 G
b00000000000000101000000000000000 g
1i
#62
0i
#63
b0000000000000000 #
b00000000000000000000000000010011 $
b000 &
1*
0,
0-
b00000000000000000000000000000000 2
b00000000000000000000000000000000 3
b00000000000000000000000000000000 4
07
b00000000000000000000000000000000 9
b0010011 :
b00000000000000000000000000000100 ?
b00000000000000000000000000000000 @
b00000000000000001000000000000100 G
b00000000000000110000000000000000 g
1i
#64
0i
#65
b0000000000000100 #
b00000000000000000000000000000100 2
b00000000000000000000000000000100 9
b00000000000000000000000000001000 ?
b00000000000000000000000000000000 G
b00000000000000110000000000000100 g
1i
#66
0i
#67
b0000000000001000 #
b00000000000000000000000010010011 $
b00000000000000000000000000001000 2
b00000000000000000000000000001000 9
b0000000000000000000000001 >
b00000000000000000000000000001100 ?
b00001 E
b00000000000000110000000000001000 g
1i
#68
0i
#69
b0000000000001100 #
b00000000000000000000000000010011 $
b00000000000000000000000000001100 2
b00000000000000000000000000001100 9
b0000000000000000000000000 >
b00000000000000000000000000010000 ?
b00000 E
b00000000000000110000000000001100 g
1i
#70
0i
#71
b0000000000010000 #
b00000000000000000000000000010000 2
b00000000000000000000000000010000 9
b00000000000000000000000000010100 ?
b00000000000000110000000000010000 g
1i
#72
0i
#73
b0000000000010100 #
b00000000000000000000000000010100 2
b00000000000000000000000000010100 9
b00000000000000000000000000011000 ?
b00000000000000110000000000010100 g
1i
#74
0i
#75
b0000000000011000 #
b00000000000000000000000011101111 $
b111 &
0'
b11 (
0*
1,
1-
b00000000000000000000000000011000 2
b00000000000000000000000000011100 3
b00000000000000000000000000011000 4
17
b00000000000000000000000000011000 9
b1101111 :
b0000000000000000000000001 >
b00000000000000000000000000011100 ?
b00000000000000000000000000011000 @
b00001 E
b00000000000000110000000000011000 g
1i
#76
0i
#77
b0000000000110000 #
b00000000000000000000000000010011 $
b000 &
1'
b00 (
1*
0,
0-
b00000000000000000000000000110000 2
b00000000000000000000000000000000 3
b00000000000000000000000000000000 4
07
b00000000000000000000000000110000 9
b0010011 :
b0000000000000000000000000 >
b00000000000000000000000000110100 ?
b00000000000000000000000000000000 @
b00000 E
b00000000000000000000000000011100 H
b00000000000000110000000000110000 g
1i
#78
0i
#79
b0000000000110100 #
b00000000000000000000000011101111 $
b111 &
0'
b11 (
0*
1,
1-
b00000000000000000000000000110100 2
b00000000000000000000000000111000 3
b00000000000000000000000000110100 4
17
b00000000000000000000000000110100 9
b1101111 :
b0000000000000000000000001 >
b00000000000000000000000000111000 ?
b00000000000000000000000000110100 @
b00001 E
b00000000000000110000000000110100 g
1i
#80
0i
