testbench/sign_extend.sv
module sign_extend #(
    parameter WIDTH = 12
)(
    input logic[WIDTH-1:0] immediate,
    input logic ImmSrc,
    output logic [31:0] ImmOp
);


    assign ImmOp = ImmSrc ? {{20{1'b0}},immediate} :{{20{1'b1}},immediate};



endmodule

testbench/alu.sv
module alu #(
    parameter DATA_WIDTH = 32
)(
    input  logic                 ctrl,
    input  logic[DATA_WIDTH-1:0] op1,
    input  logic[DATA_WIDTH-1:0] op2,
    output logic[DATA_WIDTH-1:0] out,
    output logic                 zero
);

assign out = ctrl ? (op1 - op2) : (op1 + op2);
assign zero = (out == 0);

endmodule

testbench/mux_2.sv
module mux_2 #(
    parameter VALUE_WIDTH = 32
)(
    input  logic                  sel,
    input  logic[VALUE_WIDTH-1:0] in0,
    input  logic[VALUE_WIDTH-1:0] in1,
    output logic[VALUE_WIDTH-1:0] out
);

assign out = sel ? in1 : in0;
    
endmodule

single_cycle/register_file.sv
module register_file #(
    parameter ADDR_WIDTH = 5,
              DATA_WIDTH = 32
)(
    input  logic                 clk,
    input  logic[ADDR_WIDTH-1:0] ad1,
    input  logic[ADDR_WIDTH-1:0] ad2,
    input  logic[ADDR_WIDTH-1:0] ad3,
    output logic[DATA_WIDTH-1:0] rd1,
    output logic[DATA_WIDTH-1:0] rd2,
    input  logic[DATA_WIDTH-1:0] wd3,
    input  logic                 we3,
    output logic[DATA_WIDTH-1:0] a0
);
    
logic[DATA_WIDTH-1:0] registers[2**ADDR_WIDTH-1:0];

always_comb begin
    rd1 = (ad1 == 0) ? 0 : registers[ad1]; // x0 is the constant zero register
    rd2 = (ad2 == 0) ? 0 : registers[ad2];
    a0 = registers[10];                    // a0 is register x10
end

always_ff @(posedge clk) begin
    if(we3) registers[ad3] <= wd3;
end

endmodule

testbench/control.sv
module control #(
    // bits in counter set to 8 bits
    parameter WIDTH = 32
)(
    // interface signals
    input logic EQ,
    input logic [WIDTH-1:0] instr,
    output logic RegWrite, //clk
    output logic ALUctrl, //reset
    output logic ALUsrc, // enable
    output logic ImmSrc,//increment
    output logic PCsrc //count output
);
// indicates that this is a clocked circuit

always_comb begin
    if(instr[6:0]==19) begin
        if(instr[14:12]==0) begin //addi
            assign RegWrite = 1;
        end
        assign ALUsrc = 1; //immediate
        if(instr[31]==0)  //sign extend
            assign ImmSrc = 0;
        else
            assign ImmSrc = 1;
    end 

    else if(instr[6:0]==51) begin
        assign ALUsrc = 0; //immediate
        if(instr[31:25]==0 & instr[14:12]==0) //add
            assign ALUctrl = 0;
        else if(instr[31:25]==7'b0100000 & instr[14:12]==0) //sub
            assign ALUctrl = 1;
    end

    else if(instr[6:0]==99)
        if(instr[31:25]==0 & instr[14:12]==3'b001) //bne
            assign RegWrite = 1;

    else if(instr[6:0]==23)
        if(EQ == 0) //PC+Imm
            assign PCsrc = 1;
        else //PC
            assign PCsrc = 0;

end





endmodule

rom.sv
module rom #(
    parameter ADDR_WIDTH = 16,
              DATA_WIDTH = 32
)(
    input  logic[ADDR_WIDTH-1:0] addr,
    output logic[DATA_WIDTH-1:0] dout
);

logic[DATA_WIDTH-1:0] memory[2**ADDR_WIDTH-1:0];

initial begin
    $readmemh("rom.txt", memory);
end

assign dout = memory[addr];
    
endmodule

f1_cpu/program_counter.sv
module program_counter 
(
    input logic clk,
    input logic rst,
    input logic [31:0] ImmOp,
    input logic PCsrc,
    output logic [31:0] PC
);

always_ff @(posedge clk) begin
    if(rst) 
        PC <= 0;
    else 
        if(PCsrc)
            PC <= PC + ImmOp;
        else
            PC <= PC + 4;
end


endmodule

testbench/top.sv
module top #(
    parameter DATA_WIDTH = 32
)(
    input logic clk,
    input logic rst,
    output logic[DATA_WIDTH-1:0] a0
);
logic [DATA_WIDTH-1:0] ImmOp;
logic [DATA_WIDTH-1:0] PC;
logic PCsrc;
logic [DATA_WIDTH-1:0] instr;
logic EQ;
logic RegWrite;
logic ALUctrl;
logic ALUsrc;
logic ImmSrc;
logic [DATA_WIDTH-1:0] ALUop1;
logic [DATA_WIDTH-1:0] regOp2;
logic [DATA_WIDTH-1:0] ALUop2;
logic [DATA_WIDTH-1:0] ALUout;

program_counter myCounter(
    .clk(clk),
    .rst(rst),
    .ImmOp(ImmOp),
    .PCsrc(PCsrc),
    .PC(PC)
);

rom Instr_Mem(
    .addr(PC),
    .dout(instr)
);

control Control_Unit(
    .EQ(EQ),
    .instr(instr),
    .RegWrite(RegWrite),
    .ALUctrl(ALUctrl),
    .ALUsrc(ALUsrc),
    .ImmSrc(ImmSrc),
    .PCsrc(PCsrc)
);

register_file Register(
    .clk(clk),
    .ad1(instr[19:15]),
    .ad2(instr[24:20]),
    .ad3(instr[11:7]),
    .rd1(ALUop1),
    .rd2(regOp2),
    .wd3(ALUout),
    .we3(RegWrite),
    .a0(a0)
);

mux_2 myMux(
    .sel(ALUsrc),
    .in0(regOp2),
    .in1(ImmOp),
    .out(ALUop2)
);

alu myALU(
    .ctrl(ALUctrl),
    .op1(ALUop1),
    .op2(ALUop2),
    .out(ALUout),
    .zero(EQ)
);

sign_extend mySign_extend(
    .immediate(instr[31:20]),
    .ImmSrc(ImmSrc),
    .ImmOp(ImmOp)
);

endmodule

testbench/top.vcd
$version Generated by VerilatedVcd $end
$date Fri Dec  2 10:08:31 2022 $end
$timescale 1ps $end

 $scope module TOP $end
  $var wire 32 W a0 [31:0] $end
  $var wire  1 U clk $end
  $var wire  1 V rst $end
  $scope module top $end
   $var wire  1 ) ALUctrl $end
   $var wire 32 , ALUop1 [31:0] $end
   $var wire 32 . ALUop2 [31:0] $end
   $var wire 32 / ALUout [31:0] $end
   $var wire  1 * ALUsrc $end
   $var wire 32 X DATA_WIDTH [31:0] $end
   $var wire  1 ' EQ $end
   $var wire 32 # ImmOp [31:0] $end
   $var wire  1 + ImmSrc $end
   $var wire 32 $ PC [31:0] $end
   $var wire  1 % PCsrc $end
   $var wire  1 ( RegWrite $end
   $var wire 32 W a0 [31:0] $end
   $var wire  1 U clk $end
   $var wire 32 & instr [31:0] $end
   $var wire 32 - regOp2 [31:0] $end
   $var wire  1 V rst $end
   $scope module Control_Unit $end
    $var wire  1 ) ALUctrl $end
    $var wire  1 * ALUsrc $end
    $var wire  1 ' EQ $end
    $var wire  1 + ImmSrc $end
    $var wire  1 % PCsrc $end
    $var wire  1 ( RegWrite $end
    $var wire 32 X WIDTH [31:0] $end
    $var wire 32 & instr [31:0] $end
   $upscope $end
   $scope module Instr_Mem $end
    $var wire 32 Y ADDR_WIDTH [31:0] $end
    $var wire 32 X DATA_WIDTH [31:0] $end
    $var wire 16 0 addr [15:0] $end
    $var wire 32 & dout [31:0] $end
   $upscope $end
   $scope module Register $end
    $var wire 32 Z ADDR_WIDTH [31:0] $end
    $var wire 32 X DATA_WIDTH [31:0] $end
    $var wire 32 W a0 [31:0] $end
    $var wire  5 1 ad1 [4:0] $end
    $var wire  5 2 ad2 [4:0] $end
    $var wire  5 3 ad3 [4:0] $end
    $var wire  1 U clk $end
    $var wire 32 , rd1 [31:0] $end
    $var wire 32 - rd2 [31:0] $end
    $var wire 32 4 registers[0] [31:0] $end
    $var wire 32 > registers[10] [31:0] $end
    $var wire 32 ? registers[11] [31:0] $end
    $var wire 32 @ registers[12] [31:0] $end
    $var wire 32 A registers[13] [31:0] $end
    $var wire 32 B registers[14] [31:0] $end
    $var wire 32 C registers[15] [31:0] $end
    $var wire 32 D registers[16] [31:0] $end
    $var wire 32 E registers[17] [31:0] $end
    $var wire 32 F registers[18] [31:0] $end
    $var wire 32 G registers[19] [31:0] $end
    $var wire 32 5 registers[1] [31:0] $end
    $var wire 32 H registers[20] [31:0] $end
    $var wire 32 I registers[21] [31:0] $end
    $var wire 32 J registers[22] [31:0] $end
    $var wire 32 K registers[23] [31:0] $end
    $var wire 32 L registers[24] [31:0] $end
    $var wire 32 M registers[25] [31:0] $end
    $var wire 32 N registers[26] [31:0] $end
    $var wire 32 O registers[27] [31:0] $end
    $var wire 32 P registers[28] [31:0] $end
    $var wire 32 Q registers[29] [31:0] $end
    $var wire 32 6 registers[2] [31:0] $end
    $var wire 32 R registers[30] [31:0] $end
    $var wire 32 S registers[31] [31:0] $end
    $var wire 32 7 registers[3] [31:0] $end
    $var wire 32 8 registers[4] [31:0] $end
    $var wire 32 9 registers[5] [31:0] $end
    $var wire 32 : registers[6] [31:0] $end
    $var wire 32 ; registers[7] [31:0] $end
    $var wire 32 < registers[8] [31:0] $end
    $var wire 32 = registers[9] [31:0] $end
    $var wire 32 / wd3 [31:0] $end
    $var wire  1 ( we3 $end
   $upscope $end
   $scope module myALU $end
    $var wire 32 X DATA_WIDTH [31:0] $end
    $var wire  1 ) ctrl $end
    $var wire 32 , op1 [31:0] $end
    $var wire 32 . op2 [31:0] $end
    $var wire 32 / out [31:0] $end
    $var wire  1 ' zero $end
   $upscope $end
   $scope module myCounter $end
    $var wire 32 # ImmOp [31:0] $end
    $var wire 32 $ PC [31:0] $end
    $var wire  1 % PCsrc $end
    $var wire  1 U clk $end
    $var wire  1 V rst $end
   $upscope $end
   $scope module myMux $end
    $var wire 32 X VALUE_WIDTH [31:0] $end
    $var wire 32 - in0 [31:0] $end
    $var wire 32 # in1 [31:0] $end
    $var wire 32 . out [31:0] $end
    $var wire  1 * sel $end
   $upscope $end
   $scope module mySign_extend $end
    $var wire 32 # ImmOp [31:0] $end
    $var wire  1 + ImmSrc $end
    $var wire 32 [ WIDTH [31:0] $end
    $var wire 12 T immediate [11:0] $end
   $upscope $end
  $upscope $end
 $upscope $end
$enddefinitions $end


#0
b11111111111111111111000000000000 #
b00000000000000000000000000000000 $
0%
b00000000000000000000000000010011 &
0'
1(
0)
1*
0+
b00000000000000000000000000000000 ,
b00000000000000000000000000000000 -
b11111111111111111111000000000000 .
b11111111111111111111000000000000 /
b0000000000000000 0
b00000 1
b00000 2
b00000 3
b00000000000000000000000000000000 4
b00000000000000000000000000000000 5
b00000000000000000000000000000000 6
b00000000000000000000000000000000 7
b00000000000000000000000000000000 8
b00000000000000000000000000000000 9
b00000000000000000000000000000000 :
b00000000000000000000000000000000 ;
b00000000000000000000000000000000 <
b00000000000000000000000000000000 =
b00000000000000000000000000000000 >
b00000000000000000000000000000000 ?
b00000000000000000000000000000000 @
b00000000000000000000000000000000 A
b00000000000000000000000000000000 B
b00000000000000000000000000000000 C
b00000000000000000000000000000000 D
b00000000000000000000000000000000 E
b00000000000000000000000000000000 F
b00000000000000000000000000000000 G
b00000000000000000000000000000000 H
b00000000000000000000000000000000 I
b00000000000000000000000000000000 J
b00000000000000000000000000000000 K
b00000000000000000000000000000000 L
b00000000000000000000000000000000 M
b00000000000000000000000000000000 N
b00000000000000000000000000000000 O
b00000000000000000000000000000000 P
b00000000000000000000000000000000 Q
b00000000000000000000000000000000 R
b00000000000000000000000000000000 S
b000000000000 T
0U
0V
b00000000000000000000000000000000 W
b00000000000000000000000000100000 X
b00000000000000000000000000010000 Y
b00000000000000000000000000000101 Z
b00000000000000000000000000001100 [
#1
b00000000000000000000000000000100 $
b0000000000000100 0
b11111111111111111111000000000000 4
1U
#2
0U
#3
b00000000000000000000000000001000 $
b00000000000000000000000010010011 &
b0000000000001000 0
b00001 3
1U
#4
0U
#5
b00000000000000000000000000001100 $
b00000000000000000000000000010011 &
b0000000000001100 0
b00000 3
b11111111111111111111000000000000 5
1U
#6
0U
#7
b00000000000000000000000000010000 $
b00000000000000000000000011100011 &
b0000000000010000 0
b00001 3
1U
#8
0U
#9
b00000000000000000000000000010100 $
b0000000000010100 0
1U
#10
0U
#11
b00000000000000000000000000011000 $
b00000000000000000000000000000000 &
b0000000000011000 0
b00000 3
1U
#12
0U
#13
b00000000000000000000000000011100 $
b0000000000011100 0
1U
#14
0U
#15
b00000000000000000000000000100000 $
b0000000000100000 0
1U
#16
0U
#17
b00000000000000000000000000100100 $
b0000000000100100 0
1U
#18
0U
#19
b00000000000000000000000000101000 $
b0000000000101000 0
1U
#20
0U
#21
b00000000000000000000000000101100 $
b0000000000101100 0
1U
#22
0U
#23
b00000000000000000000000000110000 $
b0000000000110000 0
1U
#24
0U
#25
b00000000000000000000000000110100 $
b0000000000110100 0
1U
#26
0U
#27
b00000000000000000000000000111000 $
b0000000000111000 0
1U
#28
0U
#29
b00000000000000000000000000111100 $
b0000000000111100 0
1U
#30
0U
#31
b00000000000000000000000001000000 $
b0000000001000000 0
1U
#32
0U
#33
b00000000000000000000000001000100 $
b0000000001000100 0
1U
#34
0U
#35
b00000000000000000000000001001000 $
b0000000001001000 0
1U
#36
0U
#37
b00000000000000000000000001001100 $
b0000000001001100 0
1U
#38
0U
#39
b00000000000000000000000001010000 $
b0000000001010000 0
1U
#40
0U
#41
b00000000000000000000000001010100 $
b0000000001010100 0
1U
#42
0U
#43
b00000000000000000000000001011000 $
b0000000001011000 0
1U
#44
0U
#45
b00000000000000000000000001011100 $
b0000000001011100 0
1U
#46
0U
#47
b00000000000000000000000001100000 $
b0000000001100000 0
1U
#48
0U
#49
b00000000000000000000000001100100 $
b0000000001100100 0
1U
#50
0U
#51
b00000000000000000000000001101000 $
b0000000001101000 0
1U
#52
0U
#53
b00000000000000000000000001101100 $
b0000000001101100 0
1U
#54
0U
#55
b00000000000000000000000001110000 $
b0000000001110000 0
1U
#56
0U
#57
b00000000000000000000000001110100 $
b0000000001110100 0
1U
#58
0U
#59
b00000000000000000000000001111000 $
b0000000001111000 0
1U
#60
0U
#61
b00000000000000000000000001111100 $
b0000000001111100 0
1U
#62
0U
#63
b00000000000000000000000010000000 $
b0000000010000000 0
1U
#64
0U
#65
b00000000000000000000000010000100 $
b0000000010000100 0
1U
#66
0U
#67
b00000000000000000000000010001000 $
b0000000010001000 0
1U
#68
0U
#69
b00000000000000000000000010001100 $
b0000000010001100 0
1U
#70
0U
#71
b00000000000000000000000010010000 $
b0000000010010000 0
1U
#72
0U
#73
b00000000000000000000000010010100 $
b0000000010010100 0
1U
#74
0U
#75
b00000000000000000000000010011000 $
b0000000010011000 0
1U
#76
0U
#77
b00000000000000000000000010011100 $
b0000000010011100 0
1U
#78
0U
#79
b00000000000000000000000010100000 $
b0000000010100000 0
1U
#80
0U
#81
b00000000000000000000000010100100 $
b0000000010100100 0
1U
#82
0U
#83
b00000000000000000000000010101000 $
b0000000010101000 0
1U
#84
0U
#85
b00000000000000000000000010101100 $
b0000000010101100 0
1U
#86
0U
#87
b00000000000000000000000010110000 $
b0000000010110000 0
1U
#88
0U
#89
b00000000000000000000000010110100 $
b0000000010110100 0
1U
#90
0U
#91
b00000000000000000000000010111000 $
b0000000010111000 0
1U
#92
0U
#93
b00000000000000000000000010111100 $
b0000000010111100 0
1U
#94
0U
#95
b00000000000000000000000011000000 $
b0000000011000000 0
1U
#96
0U
#97
b00000000000000000000000011000100 $
b0000000011000100 0
1U
#98
0U
#99
b00000000000000000000000011001000 $
b0000000011001000 0
1U
#100
0U
#101
b00000000000000000000000011001100 $
b0000000011001100 0
1U
#102
0U
#103
b00000000000000000000000011010000 $
b0000000011010000 0
1U
#104
0U
#105
b00000000000000000000000011010100 $
b0000000011010100 0
1U
#106
0U
#107
b00000000000000000000000011011000 $
b0000000011011000 0
1U
#108
0U
#109
b00000000000000000000000011011100 $
b0000000011011100 0
1U
#110
0U
#111
b00000000000000000000000011100000 $
b0000000011100000 0
1U
#112
0U
#113
b00000000000000000000000011100100 $
b0000000011100100 0
1U
#114
0U
#115
b00000000000000000000000011101000 $
b0000000011101000 0
1U
#116
0U
#117
b00000000000000000000000011101100 $
b0000000011101100 0
1U
#118
0U
#119
b00000000000000000000000011110000 $
b0000000011110000 0
1U
#120
0U
#121
b00000000000000000000000011110100 $
b0000000011110100 0
1U
#122
0U
#123
b00000000000000000000000011111000 $
b0000000011111000 0
1U
#124
0U
#125
b00000000000000000000000011111100 $
b0000000011111100 0
1U
#126
0U
#127
b00000000000000000000000100000000 $
b0000000100000000 0
1U
#128
0U
#129
b00000000000000000000000100000100 $
b0000000100000100 0
1U
#130
0U
#131
b00000000000000000000000100001000 $
b0000000100001000 0
1U
#132
0U
#133
b00000000000000000000000100001100 $
b0000000100001100 0
1U
#134
0U
#135
b00000000000000000000000100010000 $
b0000000100010000 0
1U
#136
0U
#137
b00000000000000000000000100010100 $
b0000000100010100 0
1U
#138
0U
#139
b00000000000000000000000100011000 $
b0000000100011000 0
1U
#140
0U
#141
b00000000000000000000000100011100 $
b0000000100011100 0
1U
#142
0U
#143
b00000000000000000000000100100000 $
b0000000100100000 0
1U
#144
0U
#145
b00000000000000000000000100100100 $
b0000000100100100 0
1U
#146
0U
#147
b00000000000000000000000100101000 $
b0000000100101000 0
1U
#148
0U
#149
b00000000000000000000000100101100 $
b0000000100101100 0
1U
#150
0U
#151
b00000000000000000000000100110000 $
b0000000100110000 0
1U
#152
0U
#153
b00000000000000000000000100110100 $
b0000000100110100 0
1U
#154
0U
#155
b00000000000000000000000100111000 $
b0000000100111000 0
1U
#156
0U
#157
b00000000000000000000000100111100 $
b0000000100111100 0
1U
#158
0U
#159
b00000000000000000000000101000000 $
b0000000101000000 0
1U
#160
0U
#161
b00000000000000000000000101000100 $
b0000000101000100 0
1U
#162
0U
#163
b00000000000000000000000101001000 $
b0000000101001000 0
1U
#164
0U
#165
b00000000000000000000000101001100 $
b0000000101001100 0
1U
#166
0U
#167
b00000000000000000000000101010000 $
b0000000101010000 0
1U
#168
0U
#169
b00000000000000000000000101010100 $
b0000000101010100 0
1U
#170
0U
#171
b00000000000000000000000101011000 $
b0000000101011000 0
1U
#172
0U
#173
b00000000000000000000000101011100 $
b0000000101011100 0
1U
#174
0U
#175
b00000000000000000000000101100000 $
b0000000101100000 0
1U
#176
0U
#177
b00000000000000000000000101100100 $
b0000000101100100 0
1U
#178
0U
#179
b00000000000000000000000101101000 $
b0000000101101000 0
1U
#180
0U
#181
b00000000000000000000000101101100 $
b0000000101101100 0
1U
#182
0U
#183
b00000000000000000000000101110000 $
b0000000101110000 0
1U
#184
0U
#185
b00000000000000000000000101110100 $
b0000000101110100 0
1U
#186
0U
#187
b00000000000000000000000101111000 $
b0000000101111000 0
1U
#188
0U
#189
b00000000000000000000000101111100 $
b0000000101111100 0
1U
#190
0U
#191
b00000000000000000000000110000000 $
b0000000110000000 0
1U
#192
0U
#193
b00000000000000000000000110000100 $
b0000000110000100 0
1U
#194
0U
#195
b00000000000000000000000110001000 $
b0000000110001000 0
1U
#196
0U
#197
b00000000000000000000000110001100 $
b0000000110001100 0
1U
#198
0U
#199
b00000000000000000000000110010000 $
b0000000110010000 0
1U
#200
0U
#201
b00000000000000000000000110010100 $
b0000000110010100 0
1U
#202
0U
#203
b00000000000000000000000110011000 $
b0000000110011000 0
1U
#204
0U
#205
b00000000000000000000000110011100 $
b0000000110011100 0
1U
#206
0U
#207
b00000000000000000000000110100000 $
b0000000110100000 0
1U
#208
0U
#209
b00000000000000000000000110100100 $
b0000000110100100 0
1U
#210
0U
#211
b00000000000000000000000110101000 $
b0000000110101000 0
1U
#212
0U
#213
b00000000000000000000000110101100 $
b0000000110101100 0
1U
#214
0U
#215
b00000000000000000000000110110000 $
b0000000110110000 0
1U
#216
0U
#217
b00000000000000000000000110110100 $
b0000000110110100 0
1U
#218
0U
#219
b00000000000000000000000110111000 $
b0000000110111000 0
1U
#220
0U
#221
b00000000000000000000000110111100 $
b0000000110111100 0
1U
#222
0U
#223
b00000000000000000000000111000000 $
b0000000111000000 0
1U
#224
0U
#225
b00000000000000000000000111000100 $
b0000000111000100 0
1U
#226
0U
#227
b00000000000000000000000111001000 $
b0000000111001000 0
1U
#228
0U
#229
b00000000000000000000000111001100 $
b0000000111001100 0
1U
#230
0U
#231
b00000000000000000000000111010000 $
b0000000111010000 0
1U
#232
0U
#233
b00000000000000000000000111010100 $
b0000000111010100 0
1U
#234
0U
#235
b00000000000000000000000111011000 $
b0000000111011000 0
1U
#236
0U
#237
b00000000000000000000000111011100 $
b0000000111011100 0
1U
#238
0U
#239
b00000000000000000000000111100000 $
b0000000111100000 0
1U
#240
0U
#241
b00000000000000000000000111100100 $
b0000000111100100 0
1U
#242
0U
#243
b00000000000000000000000111101000 $
b0000000111101000 0
1U
#244
0U
#245
b00000000000000000000000111101100 $
b0000000111101100 0
1U
#246
0U
#247
b00000000000000000000000111110000 $
b0000000111110000 0
1U
#248
0U
#249
b00000000000000000000000111110100 $
b0000000111110100 0
1U
#250
0U
#251
b00000000000000000000000111111000 $
b0000000111111000 0
1U
#252
0U
#253
b00000000000000000000000111111100 $
b0000000111111100 0
1U
#254
0U
#255
b00000000000000000000001000000000 $
b0000001000000000 0
1U
#256
0U
#257
b00000000000000000000001000000100 $
b0000001000000100 0
1U
#258
0U
#259
b00000000000000000000001000001000 $
b0000001000001000 0
1U
#260
0U
#261
b00000000000000000000001000001100 $
b0000001000001100 0
1U
#262
0U
#263
b00000000000000000000001000010000 $
b0000001000010000 0
1U
#264
0U
#265
b00000000000000000000001000010100 $
b0000001000010100 0
1U
#266
0U
#267
b00000000000000000000001000011000 $
b0000001000011000 0
1U
#268
0U
#269
b00000000000000000000001000011100 $
b0000001000011100 0
1U
#270
0U
#271
b00000000000000000000001000100000 $
b0000001000100000 0
1U
#272
0U
#273
b00000000000000000000001000100100 $
b0000001000100100 0
1U
#274
0U
#275
b00000000000000000000001000101000 $
b0000001000101000 0
1U
#276
0U
#277
b00000000000000000000001000101100 $
b0000001000101100 0
1U
#278
0U
#279
b00000000000000000000001000110000 $
b0000001000110000 0
1U
#280
0U
#281
b00000000000000000000001000110100 $
b0000001000110100 0
1U
#282
0U
#283
b00000000000000000000001000111000 $
b0000001000111000 0
1U
#284
0U
#285
b00000000000000000000001000111100 $
b0000001000111100 0
1U
#286
0U
#287
b00000000000000000000001001000000 $
b0000001001000000 0
1U
#288
0U
#289
b00000000000000000000001001000100 $
b0000001001000100 0
1U
#290
0U
#291
b00000000000000000000001001001000 $
b0000001001001000 0
1U
#292
0U
#293
b00000000000000000000001001001100 $
b0000001001001100 0
1U
#294
0U
#295
b00000000000000000000001001010000 $
b0000001001010000 0
1U
#296
0U
#297
b00000000000000000000001001010100 $
b0000001001010100 0
1U
#298
0U
#299
b00000000000000000000001001011000 $
b0000001001011000 0
1U
#300
0U
#301
b00000000000000000000001001011100 $
b0000001001011100 0
1U
#302
0U
#303
b00000000000000000000001001100000 $
b0000001001100000 0
1U
#304
0U
#305
b00000000000000000000001001100100 $
b0000001001100100 0
1U
#306
0U
#307
b00000000000000000000001001101000 $
b0000001001101000 0
1U
#308
0U
#309
b00000000000000000000001001101100 $
b0000001001101100 0
1U
#310
0U
#311
b00000000000000000000001001110000 $
b0000001001110000 0
1U
#312
0U
#313
b00000000000000000000001001110100 $
b0000001001110100 0
1U
#314
0U
#315
b00000000000000000000001001111000 $
b0000001001111000 0
1U
#316
0U
#317
b00000000000000000000001001111100 $
b0000001001111100 0
1U
#318
0U
#319
b00000000000000000000001010000000 $
b0000001010000000 0
1U
#320
0U
#321
b00000000000000000000001010000100 $
b0000001010000100 0
1U
#322
0U
#323
b00000000000000000000001010001000 $
b0000001010001000 0
1U
#324
0U
#325
b00000000000000000000001010001100 $
b0000001010001100 0
1U
#326
0U
#327
b00000000000000000000001010010000 $
b0000001010010000 0
1U
#328
0U
#329
b00000000000000000000001010010100 $
b0000001010010100 0
1U
#330
0U
#331
b00000000000000000000001010011000 $
b0000001010011000 0
1U
#332
0U
#333
b00000000000000000000001010011100 $
b0000001010011100 0
1U
#334
0U
#335
b00000000000000000000001010100000 $
b0000001010100000 0
1U
#336
0U
#337
b00000000000000000000001010100100 $
b0000001010100100 0
1U
#338
0U
#339
b00000000000000000000001010101000 $
b0000001010101000 0
1U
#340
0U
#341
b00000000000000000000001010101100 $
b0000001010101100 0
1U
#342
0U
#343
b00000000000000000000001010110000 $
b0000001010110000 0
1U
#344
0U
#345
b00000000000000000000001010110100 $
b0000001010110100 0
1U
#346
0U
#347
b00000000000000000000001010111000 $
b0000001010111000 0
1U
#348
0U
#349
b00000000000000000000001010111100 $
b0000001010111100 0
1U
#350
0U
#351
b00000000000000000000001011000000 $
b0000001011000000 0
1U
#352
0U
#353
b00000000000000000000001011000100 $
b0000001011000100 0
1U
#354
0U
#355
b00000000000000000000001011001000 $
b0000001011001000 0
1U
#356
0U
#357
b00000000000000000000001011001100 $
b0000001011001100 0
1U
#358
0U
#359
b00000000000000000000001011010000 $
b0000001011010000 0
1U
#360
0U
#361
b00000000000000000000001011010100 $
b0000001011010100 0
1U
#362
0U
#363
b00000000000000000000001011011000 $
b0000001011011000 0
1U
#364
0U
#365
b00000000000000000000001011011100 $
b0000001011011100 0
1U
#366
0U
#367
b00000000000000000000001011100000 $
b0000001011100000 0
1U
#368
0U
#369
b00000000000000000000001011100100 $
b0000001011100100 0
1U
#370
0U
#371
b00000000000000000000001011101000 $
b0000001011101000 0
1U
#372
0U
#373
b00000000000000000000001011101100 $
b0000001011101100 0
1U
#374
0U
#375
b00000000000000000000001011110000 $
b0000001011110000 0
1U
#376
0U
#377
b00000000000000000000001011110100 $
b0000001011110100 0
1U
#378
0U
#379
b00000000000000000000001011111000 $
b0000001011111000 0
1U
#380
0U
#381
b00000000000000000000001011111100 $
b0000001011111100 0
1U
#382
0U
#383
b00000000000000000000001100000000 $
b0000001100000000 0
1U
#384
0U
#385
b00000000000000000000001100000100 $
b0000001100000100 0
1U
#386
0U
#387
b00000000000000000000001100001000 $
b0000001100001000 0
1U
#388
0U
#389
b00000000000000000000001100001100 $
b0000001100001100 0
1U
#390
0U
#391
b00000000000000000000001100010000 $
b0000001100010000 0
1U
#392
0U
#393
b00000000000000000000001100010100 $
b0000001100010100 0
1U
#394
0U
#395
b00000000000000000000001100011000 $
b0000001100011000 0
1U
#396
0U
#397
b00000000000000000000001100011100 $
b0000001100011100 0
1U
#398
0U
#399
b00000000000000000000001100100000 $
b0000001100100000 0
1U
#400
0U
#401
b00000000000000000000001100100100 $
b0000001100100100 0
1U
#402
0U
#403
b00000000000000000000001100101000 $
b0000001100101000 0
1U
#404
0U
#405
b00000000000000000000001100101100 $
b0000001100101100 0
1U
#406
0U
#407
b00000000000000000000001100110000 $
b0000001100110000 0
1U
#408
0U
#409
b00000000000000000000001100110100 $
b0000001100110100 0
1U
#410
0U
#411
b00000000000000000000001100111000 $
b0000001100111000 0
1U
#412
0U
#413
b00000000000000000000001100111100 $
b0000001100111100 0
1U
#414
0U
#415
b00000000000000000000001101000000 $
b0000001101000000 0
1U
#416
0U
#417
b00000000000000000000001101000100 $
b0000001101000100 0
1U
#418
0U
#419
b00000000000000000000001101001000 $
b0000001101001000 0
1U
#420
0U
#421
b00000000000000000000001101001100 $
b0000001101001100 0
1U
#422
0U
#423
b00000000000000000000001101010000 $
b0000001101010000 0
1U
#424
0U
#425
b00000000000000000000001101010100 $
b0000001101010100 0
1U
#426
0U
#427
b00000000000000000000001101011000 $
b0000001101011000 0
1U
#428
0U
#429
b00000000000000000000001101011100 $
b0000001101011100 0
1U
#430
0U
#431
b00000000000000000000001101100000 $
b0000001101100000 0
1U
#432
0U
#433
b00000000000000000000001101100100 $
b0000001101100100 0
1U
#434
0U
#435
b00000000000000000000001101101000 $
b0000001101101000 0
1U
#436
0U
#437
b00000000000000000000001101101100 $
b0000001101101100 0
1U
#438
0U
#439
b00000000000000000000001101110000 $
b0000001101110000 0
1U
#440
0U
#441
b00000000000000000000001101110100 $
b0000001101110100 0
1U
#442
0U
#443
b00000000000000000000001101111000 $
b0000001101111000 0
1U
#444
0U
#445
b00000000000000000000001101111100 $
b0000001101111100 0
1U
#446
0U
#447
b00000000000000000000001110000000 $
b0000001110000000 0
1U
#448
0U
#449
b00000000000000000000001110000100 $
b0000001110000100 0
1U
#450
0U
#451
b00000000000000000000001110001000 $
b0000001110001000 0
1U
#452
0U
#453
b00000000000000000000001110001100 $
b0000001110001100 0
1U
#454
0U
#455
b00000000000000000000001110010000 $
b0000001110010000 0
1U
#456
0U
#457
b00000000000000000000001110010100 $
b0000001110010100 0
1U
#458
0U
#459
b00000000000000000000001110011000 $
b0000001110011000 0
1U
#460
0U
#461
b00000000000000000000001110011100 $
b0000001110011100 0
1U
#462
0U
#463
b00000000000000000000001110100000 $
b0000001110100000 0
1U
#464
0U
#465
b00000000000000000000001110100100 $
b0000001110100100 0
1U
#466
0U
#467
b00000000000000000000001110101000 $
b0000001110101000 0
1U
#468
0U
#469
b00000000000000000000001110101100 $
b0000001110101100 0
1U
#470
0U
#471
b00000000000000000000001110110000 $
b0000001110110000 0
1U
#472
0U
#473
b00000000000000000000001110110100 $
b0000001110110100 0
1U
#474
0U
#475
b00000000000000000000001110111000 $
b0000001110111000 0
1U
#476
0U
#477
b00000000000000000000001110111100 $
b0000001110111100 0
1U
#478
0U
#479
b00000000000000000000001111000000 $
b0000001111000000 0
1U
#480
0U
#481
b00000000000000000000001111000100 $
b0000001111000100 0
1U
#482
0U
#483
b00000000000000000000001111001000 $
b0000001111001000 0
1U
#484
0U
#485
b00000000000000000000001111001100 $
b0000001111001100 0
1U
#486
0U
#487
b00000000000000000000001111010000 $
b0000001111010000 0
1U
#488
0U
#489
b00000000000000000000001111010100 $
b0000001111010100 0
1U
#490
0U
#491
b00000000000000000000001111011000 $
b0000001111011000 0
1U
#492
0U
#493
b00000000000000000000001111011100 $
b0000001111011100 0
1U
#494
0U
#495
b00000000000000000000001111100000 $
b0000001111100000 0
1U
#496
0U
#497
b00000000000000000000001111100100 $
b0000001111100100 0
1U
#498
0U
#499
b00000000000000000000001111101000 $
b0000001111101000 0
1U
#500
0U
#501
b00000000000000000000001111101100 $
b0000001111101100 0
1U
#502
0U
#503
b00000000000000000000001111110000 $
b0000001111110000 0
1U
#504
0U
