alu/alu.sv
module alu #(
    parameter DATA_WIDTH = 32
)(
    input  logic[2:0]            ctrl,
    input  logic[DATA_WIDTH-1:0] op1, op2,
    output logic[DATA_WIDTH-1:0] out,
    output logic                 zero, less_than_unsigned, less_than_signed
);

always_comb begin
    case(ctrl)
        0: out = op1 + op2;
        1: out = op1 - op2;
        2: out = op1 & op2;
        3: out = op1 | op2;
        4: out = op1 ^ op2;
        5: out = op1 << op2;
        6: out = op1 >> op2;
        default: out = 0;
    endcase
end

always_comb begin
    zero = (out == 0);
    unsigned_less_than = (unsigned'(op1) < unsigned'(op2));
    signed_less_than = (signed'(op1) < signed'(op2));
end

endmodule

alu/alu.vcd
$version Generated by VerilatedVcd $end
$date Thu Dec  8 13:40:43 2022 $end
$timescale 1ps $end

 $scope module TOP $end
  $var wire  3 # ctrl [2:0] $end
  $var wire  1 ) less_than_signed $end
  $var wire  1 ( less_than_unsigned $end
  $var wire 32 $ op1 [31:0] $end
  $var wire 32 % op2 [31:0] $end
  $var wire 32 & out [31:0] $end
  $var wire  1 ' zero $end
  $scope module alu $end
   $var wire 32 * DATA_WIDTH [31:0] $end
   $var wire  3 # ctrl [2:0] $end
   $var wire  1 ) less_than_signed $end
   $var wire  1 ( less_than_unsigned $end
   $var wire 32 $ op1 [31:0] $end
   $var wire 32 % op2 [31:0] $end
   $var wire 32 & out [31:0] $end
   $var wire  1 ' zero $end
  $upscope $end
 $upscope $end
$enddefinitions $end


#0
b000 #
b00000000000000000000000000000000 $
b00000000000000000000000000000001 %
b00000000000000000000000000000001 &
0'
1(
1)
b00000000000000000000000000100000 *
#1
#2
b00000000000000000000000000000001 $
b00000000000000000000000000000010 &
0(
0)
#3
#4
b00000000000000000000000000000010 $
b00000000000000000000000000000011 &
#5
#6
b00000000000000000000000000000011 $
b00000000000000000000000000000100 &
#7
#8
b00000000000000000000000000000100 $
b00000000000000000000000000000101 &
#9
#10
b00000000000000000000000000000101 $
b00000000000000000000000000000110 &
#11
#12
b001 #
b00000000000000000000000000000110 $
b00000000000000000000000000000110 %
b00000000000000000000000000000000 &
1'
#13
#14
b00000000000000000000000000000111 $
b00000000000000000000000000000111 %
#15
#16
b00000000000000000000000000001000 $
b00000000000000000000000000001000 %
#17
#18
b00000000000000000000000000001001 $
b00000000000000000000000000001001 %
#19
#20
b00000000000000000000000000001010 $
b00000000000000000000000000001010 %
#21
#22
b010 #
b00000000000000000000000000001011 $
b00000000000000000000000000001100 %
b00000000000000000000000000001000 &
0'
1(
1)
#23
#24
b00000000000000000000000000001100 $
b00000000000000000000000000001101 %
b00000000000000000000000000001100 &
#25
#26
b00000000000000000000000000001101 $
b00000000000000000000000000001110 %
#27
#28
b00000000000000000000000000001110 $
b00000000000000000000000000001111 %
b00000000000000000000000000001110 &
#29
#30
b00000000000000000000000000001111 $
b00000000000000000000000000010000 %
b00000000000000000000000000000000 &
1'
#31
#32
b011 #
b00000000000000000000000000010000 $
b00000000000000000000000000010001 %
b00000000000000000000000000010001 &
0'
#33
#34
b00000000000000000000000000010001 $
b00000000000000000000000000010010 %
b00000000000000000000000000010011 &
#35
#36
b00000000000000000000000000010010 $
b00000000000000000000000000010011 %
#37
#38
b00000000000000000000000000010011 $
b00000000000000000000000000010100 %
b00000000000000000000000000010111 &
#39
#40
b00000000000000000000000000010100 $
b00000000000000000000000000010101 %
b00000000000000000000000000010101 &
#41
#42
b100 #
b00000000000000000000000000010101 $
b00000000000000000000000000010110 %
b00000000000000000000000000000011 &
#43
#44
b00000000000000000000000000010110 $
b00000000000000000000000000010111 %
b00000000000000000000000000000001 &
#45
#46
b00000000000000000000000000010111 $
b00000000000000000000000000011000 %
b00000000000000000000000000001111 &
#47
#48
b00000000000000000000000000011000 $
b00000000000000000000000000011001 %
b00000000000000000000000000000001 &
#49
#50
b00000000000000000000000000011001 $
b00000000000000000000000000011010 %
b00000000000000000000000000000011 &
#51
#52
b101 #
b00000000000000000000000000011010 $
b00000000000000000000000000000010 %
b00000000000000000000000001101000 &
0(
0)
#53
#54
b00000000000000000000000000011011 $
b00000000000000000000000001101100 &
#55
#56
b00000000000000000000000000011100 $
b00000000000000000000000001110000 &
#57
#58
b00000000000000000000000000011101 $
b00000000000000000000000001110100 &
#59
#60
b00000000000000000000000000011110 $
b00000000000000000000000001111000 &
#61
#62
b110 #
b00000000000000000000000000011111 $
b00000000000000000000000000000101 %
b00000000000000000000000000000000 &
1'
#63
#64
b00000000000000000000000000100000 $
b00000000000000000000000000000001 &
0'
#65
#66
b00000000000000000000000000100001 $
#67
#68
b00000000000000000000000000100010 $
#69
#70
b00000000000000000000000000100011 $
#71
#72
b111 #
b00000000000000000000000000100100 $
b00000000000000000000000000100100 %
b00000000000000000000000000100100 &
#73
#74
b00000000000000000000000000100101 $
b00000000000000000000000000100101 %
b00000000000000000000000000100101 &
#75
#76
b00000000000000000000000000100110 $
b00000000000000000000000000100110 %
b00000000000000000000000000100110 &
#77
#78
b00000000000000000000000000100111 $
b00000000000000000000000000100111 %
b00000000000000000000000000100111 &
#79
#80
b00000000000000000000000000101000 $
b00000000000000000000000000101000 %
b00000000000000000000000000101000 &
#81
#82
b00000000000000000000000000101001 $
b00000000000000000000000000101001 %
b00000000000000000000000000101001 &
#83
#84
b00000000000000000000000000101010 $
b00000000000000000000000000101010 %
b00000000000000000000000000101010 &
#85
#86
b00000000000000000000000000101011 $
b00000000000000000000000000101011 %
b00000000000000000000000000101011 &
#87
#88
b00000000000000000000000000101100 $
b00000000000000000000000000101100 %
b00000000000000000000000000101100 &
#89
#90
b00000000000000000000000000101101 $
b00000000000000000000000000101101 %
b00000000000000000000000000101101 &
#91
#92
b00000000000000000000000000101110 $
b00000000000000000000000000101110 %
b00000000000000000000000000101110 &
#93
#94
b00000000000000000000000000101111 $
b00000000000000000000000000101111 %
b00000000000000000000000000101111 &
#95
#96
b00000000000000000000000000110000 $
b00000000000000000000000000110000 %
b00000000000000000000000000110000 &
#97
#98
b00000000000000000000000000110001 $
b00000000000000000000000000110001 %
b00000000000000000000000000110001 &
#99
#100
b00000000000000000000000000110010 $
b00000000000000000000000000110010 %
b00000000000000000000000000110010 &
#101
#102
b00000000000000000000000000110011 $
b00000000000000000000000000110011 %
b00000000000000000000000000110011 &
#103
#104
b00000000000000000000000000110100 $
b00000000000000000000000000110100 %
b00000000000000000000000000110100 &
#105
#106
b00000000000000000000000000110101 $
b00000000000000000000000000110101 %
b00000000000000000000000000110101 &
#107
#108
b00000000000000000000000000110110 $
b00000000000000000000000000110110 %
b00000000000000000000000000110110 &
#109
#110
b00000000000000000000000000110111 $
b00000000000000000000000000110111 %
b00000000000000000000000000110111 &
#111
#112
b00000000000000000000000000111000 $
b00000000000000000000000000111000 %
b00000000000000000000000000111000 &
#113
#114
b00000000000000000000000000111001 $
b00000000000000000000000000111001 %
b00000000000000000000000000111001 &
#115
#116
b00000000000000000000000000111010 $
b00000000000000000000000000111010 %
b00000000000000000000000000111010 &
#117
#118
b00000000000000000000000000111011 $
b00000000000000000000000000111011 %
b00000000000000000000000000111011 &
#119
#120
b00000000000000000000000000111100 $
b00000000000000000000000000111100 %
b00000000000000000000000000111100 &
#121
#122
b00000000000000000000000000111101 $
b00000000000000000000000000111101 %
b00000000000000000000000000111101 &
#123
#124
b00000000000000000000000000111110 $
b00000000000000000000000000111110 %
b00000000000000000000000000111110 &
#125
#126
b00000000000000000000000000111111 $
b00000000000000000000000000111111 %
b00000000000000000000000000111111 &
#127
#128
b00000000000000000000000001000000 $
b00000000000000000000000001000000 %
b00000000000000000000000001000000 &
#129
#130
b00000000000000000000000001000001 $
b00000000000000000000000001000001 %
b00000000000000000000000001000001 &
#131
#132
b00000000000000000000000001000010 $
b00000000000000000000000001000010 %
b00000000000000000000000001000010 &
#133
#134
b00000000000000000000000001000011 $
b00000000000000000000000001000011 %
b00000000000000000000000001000011 &
#135
#136
b00000000000000000000000001000100 $
b00000000000000000000000001000100 %
b00000000000000000000000001000100 &
#137
#138
b00000000000000000000000001000101 $
b00000000000000000000000001000101 %
b00000000000000000000000001000101 &
#139
#140
b00000000000000000000000001000110 $
b00000000000000000000000001000110 %
b00000000000000000000000001000110 &
#141
#142
b00000000000000000000000001000111 $
b00000000000000000000000001000111 %
b00000000000000000000000001000111 &
#143
#144
b00000000000000000000000001001000 $
b00000000000000000000000001001000 %
b00000000000000000000000001001000 &
#145
#146
b00000000000000000000000001001001 $
b00000000000000000000000001001001 %
b00000000000000000000000001001001 &
#147
#148
b00000000000000000000000001001010 $
b00000000000000000000000001001010 %
b00000000000000000000000001001010 &
#149
#150
b00000000000000000000000001001011 $
b00000000000000000000000001001011 %
b00000000000000000000000001001011 &
#151
#152
b00000000000000000000000001001100 $
b00000000000000000000000001001100 %
b00000000000000000000000001001100 &
#153
#154
b00000000000000000000000001001101 $
b00000000000000000000000001001101 %
b00000000000000000000000001001101 &
#155
#156
b00000000000000000000000001001110 $
b00000000000000000000000001001110 %
b00000000000000000000000001001110 &
#157
#158
b00000000000000000000000001001111 $
b00000000000000000000000001001111 %
b00000000000000000000000001001111 &
#159
#160
b00000000000000000000000001010000 $
b00000000000000000000000001010000 %
b00000000000000000000000001010000 &
#161
#162
b00000000000000000000000001010001 $
b00000000000000000000000001010001 %
b00000000000000000000000001010001 &
#163
#164
b00000000000000000000000001010010 $
b00000000000000000000000001010010 %
b00000000000000000000000001010010 &
#165
#166
b00000000000000000000000001010011 $
b00000000000000000000000001010011 %
b00000000000000000000000001010011 &
#167
#168
b00000000000000000000000001010100 $
b00000000000000000000000001010100 %
b00000000000000000000000001010100 &
#169
#170
b00000000000000000000000001010101 $
b00000000000000000000000001010101 %
b00000000000000000000000001010101 &
#171
#172
b00000000000000000000000001010110 $
b00000000000000000000000001010110 %
b00000000000000000000000001010110 &
#173
#174
b00000000000000000000000001010111 $
b00000000000000000000000001010111 %
b00000000000000000000000001010111 &
#175
#176
b00000000000000000000000001011000 $
b00000000000000000000000001011000 %
b00000000000000000000000001011000 &
#177
#178
b00000000000000000000000001011001 $
b00000000000000000000000001011001 %
b00000000000000000000000001011001 &
#179
#180
b00000000000000000000000001011010 $
b00000000000000000000000001011010 %
b00000000000000000000000001011010 &
#181
#182
b00000000000000000000000001011011 $
b00000000000000000000000001011011 %
b00000000000000000000000001011011 &
#183
#184
b00000000000000000000000001011100 $
b00000000000000000000000001011100 %
b00000000000000000000000001011100 &
#185
#186
b00000000000000000000000001011101 $
b00000000000000000000000001011101 %
b00000000000000000000000001011101 &
#187
#188
b00000000000000000000000001011110 $
b00000000000000000000000001011110 %
b00000000000000000000000001011110 &
#189
#190
b00000000000000000000000001011111 $
b00000000000000000000000001011111 %
b00000000000000000000000001011111 &
#191
#192
b00000000000000000000000001100000 $
b00000000000000000000000001100000 %
b00000000000000000000000001100000 &
#193
#194
b00000000000000000000000001100001 $
b00000000000000000000000001100001 %
b00000000000000000000000001100001 &
#195
#196
b00000000000000000000000001100010 $
b00000000000000000000000001100010 %
b00000000000000000000000001100010 &
#197
#198
b00000000000000000000000001100011 $
b00000000000000000000000001100011 %
b00000000000000000000000001100011 &
#199
#200
b00000000000000000000000001100100 $
b00000000000000000000000001100100 %
b00000000000000000000000001100100 &
#201
#202
b00000000000000000000000001100101 $
b00000000000000000000000001100101 %
b00000000000000000000000001100101 &
#203
#204
b00000000000000000000000001100110 $
b00000000000000000000000001100110 %
b00000000000000000000000001100110 &
#205
#206
b00000000000000000000000001100111 $
b00000000000000000000000001100111 %
b00000000000000000000000001100111 &
#207
#208
b00000000000000000000000001101000 $
b00000000000000000000000001101000 %
b00000000000000000000000001101000 &
#209
#210
b00000000000000000000000001101001 $
b00000000000000000000000001101001 %
b00000000000000000000000001101001 &
#211
#212
b00000000000000000000000001101010 $
b00000000000000000000000001101010 %
b00000000000000000000000001101010 &
#213
#214
b00000000000000000000000001101011 $
b00000000000000000000000001101011 %
b00000000000000000000000001101011 &
#215
#216
b00000000000000000000000001101100 $
b00000000000000000000000001101100 %
b00000000000000000000000001101100 &
#217
#218
b00000000000000000000000001101101 $
b00000000000000000000000001101101 %
b00000000000000000000000001101101 &
#219
#220
b00000000000000000000000001101110 $
b00000000000000000000000001101110 %
b00000000000000000000000001101110 &
#221
#222
b00000000000000000000000001101111 $
b00000000000000000000000001101111 %
b00000000000000000000000001101111 &
#223
#224
b00000000000000000000000001110000 $
b00000000000000000000000001110000 %
b00000000000000000000000001110000 &
#225
#226
b00000000000000000000000001110001 $
b00000000000000000000000001110001 %
b00000000000000000000000001110001 &
#227
#228
b00000000000000000000000001110010 $
b00000000000000000000000001110010 %
b00000000000000000000000001110010 &
#229
#230
b00000000000000000000000001110011 $
b00000000000000000000000001110011 %
b00000000000000000000000001110011 &
#231
#232
b00000000000000000000000001110100 $
b00000000000000000000000001110100 %
b00000000000000000000000001110100 &
#233
#234
b00000000000000000000000001110101 $
b00000000000000000000000001110101 %
b00000000000000000000000001110101 &
#235
#236
b00000000000000000000000001110110 $
b00000000000000000000000001110110 %
b00000000000000000000000001110110 &
#237
#238
b00000000000000000000000001110111 $
b00000000000000000000000001110111 %
b00000000000000000000000001110111 &
#239
#240
b00000000000000000000000001111000 $
b00000000000000000000000001111000 %
b00000000000000000000000001111000 &
#241
#242
b00000000000000000000000001111001 $
b00000000000000000000000001111001 %
b00000000000000000000000001111001 &
#243
#244
b00000000000000000000000001111010 $
b00000000000000000000000001111010 %
b00000000000000000000000001111010 &
#245
#246
b00000000000000000000000001111011 $
b00000000000000000000000001111011 %
b00000000000000000000000001111011 &
#247
#248
b00000000000000000000000001111100 $
b00000000000000000000000001111100 %
b00000000000000000000000001111100 &
#249
#250
b00000000000000000000000001111101 $
b00000000000000000000000001111101 %
b00000000000000000000000001111101 &
#251
#252
b00000000000000000000000001111110 $
b00000000000000000000000001111110 %
b00000000000000000000000001111110 &
#253
#254
b00000000000000000000000001111111 $
b00000000000000000000000001111111 %
b00000000000000000000000001111111 &
#255
#256
b00000000000000000000000010000000 $
b00000000000000000000000010000000 %
b00000000000000000000000010000000 &
#257
#258
b00000000000000000000000010000001 $
b00000000000000000000000010000001 %
b00000000000000000000000010000001 &
#259
#260
b00000000000000000000000010000010 $
b00000000000000000000000010000010 %
b00000000000000000000000010000010 &
#261
#262
b00000000000000000000000010000011 $
b00000000000000000000000010000011 %
b00000000000000000000000010000011 &
#263
#264
b00000000000000000000000010000100 $
b00000000000000000000000010000100 %
b00000000000000000000000010000100 &
#265
#266
b00000000000000000000000010000101 $
b00000000000000000000000010000101 %
b00000000000000000000000010000101 &
#267
#268
b00000000000000000000000010000110 $
b00000000000000000000000010000110 %
b00000000000000000000000010000110 &
#269
#270
b00000000000000000000000010000111 $
b00000000000000000000000010000111 %
b00000000000000000000000010000111 &
#271
#272
b00000000000000000000000010001000 $
b00000000000000000000000010001000 %
b00000000000000000000000010001000 &
#273
#274
b00000000000000000000000010001001 $
b00000000000000000000000010001001 %
b00000000000000000000000010001001 &
#275
#276
b00000000000000000000000010001010 $
b00000000000000000000000010001010 %
b00000000000000000000000010001010 &
#277
#278
b00000000000000000000000010001011 $
b00000000000000000000000010001011 %
b00000000000000000000000010001011 &
#279
#280
b00000000000000000000000010001100 $
b00000000000000000000000010001100 %
b00000000000000000000000010001100 &
#281
#282
b00000000000000000000000010001101 $
b00000000000000000000000010001101 %
b00000000000000000000000010001101 &
#283
#284
b00000000000000000000000010001110 $
b00000000000000000000000010001110 %
b00000000000000000000000010001110 &
#285
#286
b00000000000000000000000010001111 $
b00000000000000000000000010001111 %
b00000000000000000000000010001111 &
#287
#288
b00000000000000000000000010010000 $
b00000000000000000000000010010000 %
b00000000000000000000000010010000 &
#289
#290
b00000000000000000000000010010001 $
b00000000000000000000000010010001 %
b00000000000000000000000010010001 &
#291
#292
b00000000000000000000000010010010 $
b00000000000000000000000010010010 %
b00000000000000000000000010010010 &
#293
#294
b00000000000000000000000010010011 $
b00000000000000000000000010010011 %
b00000000000000000000000010010011 &
#295
#296
b00000000000000000000000010010100 $
b00000000000000000000000010010100 %
b00000000000000000000000010010100 &
#297
#298
b00000000000000000000000010010101 $
b00000000000000000000000010010101 %
b00000000000000000000000010010101 &
#299
#300
b00000000000000000000000010010110 $
b00000000000000000000000010010110 %
b00000000000000000000000010010110 &
#301
#302
b00000000000000000000000010010111 $
b00000000000000000000000010010111 %
b00000000000000000000000010010111 &
#303
#304
b00000000000000000000000010011000 $
b00000000000000000000000010011000 %
b00000000000000000000000010011000 &
#305
#306
b00000000000000000000000010011001 $
b00000000000000000000000010011001 %
b00000000000000000000000010011001 &
#307
#308
b00000000000000000000000010011010 $
b00000000000000000000000010011010 %
b00000000000000000000000010011010 &
#309
#310
b00000000000000000000000010011011 $
b00000000000000000000000010011011 %
b00000000000000000000000010011011 &
#311
#312
b00000000000000000000000010011100 $
b00000000000000000000000010011100 %
b00000000000000000000000010011100 &
#313
#314
b00000000000000000000000010011101 $
b00000000000000000000000010011101 %
b00000000000000000000000010011101 &
#315
#316
b00000000000000000000000010011110 $
b00000000000000000000000010011110 %
b00000000000000000000000010011110 &
#317
#318
b00000000000000000000000010011111 $
b00000000000000000000000010011111 %
b00000000000000000000000010011111 &
#319
#320
b00000000000000000000000010100000 $
b00000000000000000000000010100000 %
b00000000000000000000000010100000 &
#321
#322
b00000000000000000000000010100001 $
b00000000000000000000000010100001 %
b00000000000000000000000010100001 &
#323
#324
b00000000000000000000000010100010 $
b00000000000000000000000010100010 %
b00000000000000000000000010100010 &
#325
#326
b00000000000000000000000010100011 $
b00000000000000000000000010100011 %
b00000000000000000000000010100011 &
#327
#328
b00000000000000000000000010100100 $
b00000000000000000000000010100100 %
b00000000000000000000000010100100 &
#329
#330
b00000000000000000000000010100101 $
b00000000000000000000000010100101 %
b00000000000000000000000010100101 &
#331
#332
b00000000000000000000000010100110 $
b00000000000000000000000010100110 %
b00000000000000000000000010100110 &
#333
#334
b00000000000000000000000010100111 $
b00000000000000000000000010100111 %
b00000000000000000000000010100111 &
#335
#336
b00000000000000000000000010101000 $
b00000000000000000000000010101000 %
b00000000000000000000000010101000 &
#337
#338
b00000000000000000000000010101001 $
b00000000000000000000000010101001 %
b00000000000000000000000010101001 &
#339
#340
b00000000000000000000000010101010 $
b00000000000000000000000010101010 %
b00000000000000000000000010101010 &
#341
#342
b00000000000000000000000010101011 $
b00000000000000000000000010101011 %
b00000000000000000000000010101011 &
#343
#344
b00000000000000000000000010101100 $
b00000000000000000000000010101100 %
b00000000000000000000000010101100 &
#345
#346
b00000000000000000000000010101101 $
b00000000000000000000000010101101 %
b00000000000000000000000010101101 &
#347
#348
b00000000000000000000000010101110 $
b00000000000000000000000010101110 %
b00000000000000000000000010101110 &
#349
#350
b00000000000000000000000010101111 $
b00000000000000000000000010101111 %
b00000000000000000000000010101111 &
#351
#352
b00000000000000000000000010110000 $
b00000000000000000000000010110000 %
b00000000000000000000000010110000 &
#353
#354
b00000000000000000000000010110001 $
b00000000000000000000000010110001 %
b00000000000000000000000010110001 &
#355
#356
b00000000000000000000000010110010 $
b00000000000000000000000010110010 %
b00000000000000000000000010110010 &
#357
#358
b00000000000000000000000010110011 $
b00000000000000000000000010110011 %
b00000000000000000000000010110011 &
#359
#360
b00000000000000000000000010110100 $
b00000000000000000000000010110100 %
b00000000000000000000000010110100 &
#361
#362
b00000000000000000000000010110101 $
b00000000000000000000000010110101 %
b00000000000000000000000010110101 &
#363
#364
b00000000000000000000000010110110 $
b00000000000000000000000010110110 %
b00000000000000000000000010110110 &
#365
#366
b00000000000000000000000010110111 $
b00000000000000000000000010110111 %
b00000000000000000000000010110111 &
#367
#368
b00000000000000000000000010111000 $
b00000000000000000000000010111000 %
b00000000000000000000000010111000 &
#369
#370
b00000000000000000000000010111001 $
b00000000000000000000000010111001 %
b00000000000000000000000010111001 &
#371
#372
b00000000000000000000000010111010 $
b00000000000000000000000010111010 %
b00000000000000000000000010111010 &
#373
#374
b00000000000000000000000010111011 $
b00000000000000000000000010111011 %
b00000000000000000000000010111011 &
#375
#376
b00000000000000000000000010111100 $
b00000000000000000000000010111100 %
b00000000000000000000000010111100 &
#377
#378
b00000000000000000000000010111101 $
b00000000000000000000000010111101 %
b00000000000000000000000010111101 &
#379
#380
b00000000000000000000000010111110 $
b00000000000000000000000010111110 %
b00000000000000000000000010111110 &
#381
#382
b00000000000000000000000010111111 $
b00000000000000000000000010111111 %
b00000000000000000000000010111111 &
#383
#384
b00000000000000000000000011000000 $
b00000000000000000000000011000000 %
b00000000000000000000000011000000 &
#385
#386
b00000000000000000000000011000001 $
b00000000000000000000000011000001 %
b00000000000000000000000011000001 &
#387
#388
b00000000000000000000000011000010 $
b00000000000000000000000011000010 %
b00000000000000000000000011000010 &
#389
#390
b00000000000000000000000011000011 $
b00000000000000000000000011000011 %
b00000000000000000000000011000011 &
#391
#392
b00000000000000000000000011000100 $
b00000000000000000000000011000100 %
b00000000000000000000000011000100 &
#393
#394
b00000000000000000000000011000101 $
b00000000000000000000000011000101 %
b00000000000000000000000011000101 &
#395
#396
b00000000000000000000000011000110 $
b00000000000000000000000011000110 %
b00000000000000000000000011000110 &
#397
#398
b00000000000000000000000011000111 $
b00000000000000000000000011000111 %
b00000000000000000000000011000111 &
#399
#400
b00000000000000000000000011001000 $
b00000000000000000000000011001000 %
b00000000000000000000000011001000 &
#401
#402
b00000000000000000000000011001001 $
b00000000000000000000000011001001 %
b00000000000000000000000011001001 &
#403
#404
b00000000000000000000000011001010 $
b00000000000000000000000011001010 %
b00000000000000000000000011001010 &
#405
#406
b00000000000000000000000011001011 $
b00000000000000000000000011001011 %
b00000000000000000000000011001011 &
#407
#408
b00000000000000000000000011001100 $
b00000000000000000000000011001100 %
b00000000000000000000000011001100 &
#409
#410
b00000000000000000000000011001101 $
b00000000000000000000000011001101 %
b00000000000000000000000011001101 &
#411
#412
b00000000000000000000000011001110 $
b00000000000000000000000011001110 %
b00000000000000000000000011001110 &
#413
#414
b00000000000000000000000011001111 $
b00000000000000000000000011001111 %
b00000000000000000000000011001111 &
#415
#416
b00000000000000000000000011010000 $
b00000000000000000000000011010000 %
b00000000000000000000000011010000 &
#417
#418
b00000000000000000000000011010001 $
b00000000000000000000000011010001 %
b00000000000000000000000011010001 &
#419
#420
b00000000000000000000000011010010 $
b00000000000000000000000011010010 %
b00000000000000000000000011010010 &
#421
#422
b00000000000000000000000011010011 $
b00000000000000000000000011010011 %
b00000000000000000000000011010011 &
#423
#424
b00000000000000000000000011010100 $
b00000000000000000000000011010100 %
b00000000000000000000000011010100 &
#425
#426
b00000000000000000000000011010101 $
b00000000000000000000000011010101 %
b00000000000000000000000011010101 &
#427
#428
b00000000000000000000000011010110 $
b00000000000000000000000011010110 %
b00000000000000000000000011010110 &
#429
#430
b00000000000000000000000011010111 $
b00000000000000000000000011010111 %
b00000000000000000000000011010111 &
#431
#432
b00000000000000000000000011011000 $
b00000000000000000000000011011000 %
b00000000000000000000000011011000 &
#433
#434
b00000000000000000000000011011001 $
b00000000000000000000000011011001 %
b00000000000000000000000011011001 &
#435
#436
b00000000000000000000000011011010 $
b00000000000000000000000011011010 %
b00000000000000000000000011011010 &
#437
#438
b00000000000000000000000011011011 $
b00000000000000000000000011011011 %
b00000000000000000000000011011011 &
#439
#440
b00000000000000000000000011011100 $
b00000000000000000000000011011100 %
b00000000000000000000000011011100 &
#441
#442
b00000000000000000000000011011101 $
b00000000000000000000000011011101 %
b00000000000000000000000011011101 &
#443
#444
b00000000000000000000000011011110 $
b00000000000000000000000011011110 %
b00000000000000000000000011011110 &
#445
#446
b00000000000000000000000011011111 $
b00000000000000000000000011011111 %
b00000000000000000000000011011111 &
#447
#448
b00000000000000000000000011100000 $
b00000000000000000000000011100000 %
b00000000000000000000000011100000 &
#449
#450
b00000000000000000000000011100001 $
b00000000000000000000000011100001 %
b00000000000000000000000011100001 &
#451
#452
b00000000000000000000000011100010 $
b00000000000000000000000011100010 %
b00000000000000000000000011100010 &
#453
#454
b00000000000000000000000011100011 $
b00000000000000000000000011100011 %
b00000000000000000000000011100011 &
#455
#456
b00000000000000000000000011100100 $
b00000000000000000000000011100100 %
b00000000000000000000000011100100 &
#457
#458
b00000000000000000000000011100101 $
b00000000000000000000000011100101 %
b00000000000000000000000011100101 &
#459
#460
b00000000000000000000000011100110 $
b00000000000000000000000011100110 %
b00000000000000000000000011100110 &
#461
#462
b00000000000000000000000011100111 $
b00000000000000000000000011100111 %
b00000000000000000000000011100111 &
#463
#464
b00000000000000000000000011101000 $
b00000000000000000000000011101000 %
b00000000000000000000000011101000 &
#465
#466
b00000000000000000000000011101001 $
b00000000000000000000000011101001 %
b00000000000000000000000011101001 &
#467
#468
b00000000000000000000000011101010 $
b00000000000000000000000011101010 %
b00000000000000000000000011101010 &
#469
#470
b00000000000000000000000011101011 $
b00000000000000000000000011101011 %
b00000000000000000000000011101011 &
#471
#472
b00000000000000000000000011101100 $
b00000000000000000000000011101100 %
b00000000000000000000000011101100 &
#473
#474
b00000000000000000000000011101101 $
b00000000000000000000000011101101 %
b00000000000000000000000011101101 &
#475
#476
b00000000000000000000000011101110 $
b00000000000000000000000011101110 %
b00000000000000000000000011101110 &
#477
#478
b00000000000000000000000011101111 $
b00000000000000000000000011101111 %
b00000000000000000000000011101111 &
#479
#480
b00000000000000000000000011110000 $
b00000000000000000000000011110000 %
b00000000000000000000000011110000 &
#481
#482
b00000000000000000000000011110001 $
b00000000000000000000000011110001 %
b00000000000000000000000011110001 &
#483
#484
b00000000000000000000000011110010 $
b00000000000000000000000011110010 %
b00000000000000000000000011110010 &
#485
#486
b00000000000000000000000011110011 $
b00000000000000000000000011110011 %
b00000000000000000000000011110011 &
#487
#488
b00000000000000000000000011110100 $
b00000000000000000000000011110100 %
b00000000000000000000000011110100 &
#489
#490
b00000000000000000000000011110101 $
b00000000000000000000000011110101 %
b00000000000000000000000011110101 &
#491
#492
b00000000000000000000000011110110 $
b00000000000000000000000011110110 %
b00000000000000000000000011110110 &
#493
#494
b00000000000000000000000011110111 $
b00000000000000000000000011110111 %
b00000000000000000000000011110111 &
#495
#496
b00000000000000000000000011111000 $
b00000000000000000000000011111000 %
b00000000000000000000000011111000 &
#497
#498
b00000000000000000000000011111001 $
b00000000000000000000000011111001 %
b00000000000000000000000011111001 &
#499
#500
b00000000000000000000000011111010 $
b00000000000000000000000011111010 %
b00000000000000000000000011111010 &
#501
#502
b00000000000000000000000011111011 $
b00000000000000000000000011111011 %
b00000000000000000000000011111011 &
#503
#504
b00000000000000000000000011111100 $
b00000000000000000000000011111100 %
b00000000000000000000000011111100 &
#505
#506
b00000000000000000000000011111101 $
b00000000000000000000000011111101 %
b00000000000000000000000011111101 &
#507
#508
b00000000000000000000000011111110 $
b00000000000000000000000011111110 %
b00000000000000000000000011111110 &
#509
#510
b00000000000000000000000011111111 $
b00000000000000000000000011111111 %
b00000000000000000000000011111111 &
#511
#512
b00000000000000000000000100000000 $
b00000000000000000000000100000000 %
b00000000000000000000000100000000 &
#513
#514
b00000000000000000000000100000001 $
b00000000000000000000000100000001 %
b00000000000000000000000100000001 &
#515
#516
b00000000000000000000000100000010 $
b00000000000000000000000100000010 %
b00000000000000000000000100000010 &
#517
#518
b00000000000000000000000100000011 $
b00000000000000000000000100000011 %
b00000000000000000000000100000011 &
#519
#520
b00000000000000000000000100000100 $
b00000000000000000000000100000100 %
b00000000000000000000000100000100 &
#521
#522
b00000000000000000000000100000101 $
b00000000000000000000000100000101 %
b00000000000000000000000100000101 &
#523
#524
b00000000000000000000000100000110 $
b00000000000000000000000100000110 %
b00000000000000000000000100000110 &
#525
#526
b00000000000000000000000100000111 $
b00000000000000000000000100000111 %
b00000000000000000000000100000111 &
#527
#528
b00000000000000000000000100001000 $
b00000000000000000000000100001000 %
b00000000000000000000000100001000 &
#529
#530
b00000000000000000000000100001001 $
b00000000000000000000000100001001 %
b00000000000000000000000100001001 &
#531
#532
b00000000000000000000000100001010 $
b00000000000000000000000100001010 %
b00000000000000000000000100001010 &
#533
#534
b00000000000000000000000100001011 $
b00000000000000000000000100001011 %
b00000000000000000000000100001011 &
#535
#536
b00000000000000000000000100001100 $
b00000000000000000000000100001100 %
b00000000000000000000000100001100 &
#537
#538
b00000000000000000000000100001101 $
b00000000000000000000000100001101 %
b00000000000000000000000100001101 &
#539
#540
b00000000000000000000000100001110 $
b00000000000000000000000100001110 %
b00000000000000000000000100001110 &
#541
#542
b00000000000000000000000100001111 $
b00000000000000000000000100001111 %
b00000000000000000000000100001111 &
#543
#544
b00000000000000000000000100010000 $
b00000000000000000000000100010000 %
b00000000000000000000000100010000 &
#545
#546
b00000000000000000000000100010001 $
b00000000000000000000000100010001 %
b00000000000000000000000100010001 &
#547
#548
b00000000000000000000000100010010 $
b00000000000000000000000100010010 %
b00000000000000000000000100010010 &
#549
#550
b00000000000000000000000100010011 $
b00000000000000000000000100010011 %
b00000000000000000000000100010011 &
#551
#552
b00000000000000000000000100010100 $
b00000000000000000000000100010100 %
b00000000000000000000000100010100 &
#553
#554
b00000000000000000000000100010101 $
b00000000000000000000000100010101 %
b00000000000000000000000100010101 &
#555
#556
b00000000000000000000000100010110 $
b00000000000000000000000100010110 %
b00000000000000000000000100010110 &
#557
#558
b00000000000000000000000100010111 $
b00000000000000000000000100010111 %
b00000000000000000000000100010111 &
#559
#560
b00000000000000000000000100011000 $
b00000000000000000000000100011000 %
b00000000000000000000000100011000 &
#561
#562
b00000000000000000000000100011001 $
b00000000000000000000000100011001 %
b00000000000000000000000100011001 &
#563
#564
b00000000000000000000000100011010 $
b00000000000000000000000100011010 %
b00000000000000000000000100011010 &
#565
#566
b00000000000000000000000100011011 $
b00000000000000000000000100011011 %
b00000000000000000000000100011011 &
#567
