alu.sv
module alu #(
    parameter DATA_WIDTH = 32
)(
    input  logic                 ctrl
    input  logic[DATA_WIDTH-1:0] op1,
    input  logic[DATA_WIDTH-1:0] op2,
    output logic[DATA_WIDTH-1:0] out,
    output logic                 zero
);

assign out = ctrl ? (op1 - op2) : (op1 + op2);
assign zero = (out == 0);

endmodule

alu/alu.vcd
$version Generated by VerilatedVcd $end
$date Mon Nov 28 20:43:12 2022 $end
$timescale 1ps $end

 $scope module TOP $end
  $var wire  1 # ctrl $end
  $var wire 32 $ op1 [31:0] $end
  $var wire 32 % op2 [31:0] $end
  $var wire 32 & out [31:0] $end
  $var wire  1 ' zero $end
  $scope module alu $end
   $var wire 32 ( DATA_WIDTH [31:0] $end
   $var wire  1 # ctrl $end
   $var wire 32 $ op1 [31:0] $end
   $var wire 32 % op2 [31:0] $end
   $var wire 32 & out [31:0] $end
   $var wire  1 ' zero $end
  $upscope $end
 $upscope $end
$enddefinitions $end


#0
0#
b00000000000000000000000000000000 $
b00000000000000000000000000000001 %
b00000000000000000000000000000001 &
0'
b00000000000000000000000000100000 (
#1
#2
b00000000000000000000000000000001 $
b00000000000000000000000000000010 &
#3
#4
b00000000000000000000000000000010 $
b00000000000000000000000000000011 &
#5
#6
b00000000000000000000000000000011 $
b00000000000000000000000000000100 &
#7
#8
b00000000000000000000000000000100 $
b00000000000000000000000000000101 &
#9
#10
b00000000000000000000000000000101 $
b00000000000000000000000000000110 &
#11
#12
b00000000000000000000000000000110 $
b00000000000000000000000000000111 &
#13
#14
b00000000000000000000000000000111 $
b00000000000000000000000000001000 &
#15
#16
b00000000000000000000000000001000 $
b00000000000000000000000000001001 &
#17
#18
b00000000000000000000000000001001 $
b00000000000000000000000000001010 &
#19
#20
b00000000000000000000000000001010 $
b00000000000000000000000000001011 &
#21
#22
b00000000000000000000000000001011 $
b00000000000000000000000000001100 &
#23
#24
b00000000000000000000000000001100 $
b00000000000000000000000000001101 &
#25
#26
b00000000000000000000000000001101 $
b00000000000000000000000000001110 &
#27
#28
b00000000000000000000000000001110 $
b00000000000000000000000000001111 &
#29
#30
b00000000000000000000000000001111 $
b00000000000000000000000000010000 &
#31
#32
b00000000000000000000000000010000 $
b00000000000000000000000000010001 &
#33
#34
b00000000000000000000000000010001 $
b00000000000000000000000000010010 &
#35
#36
b00000000000000000000000000010010 $
b00000000000000000000000000010011 &
#37
#38
b00000000000000000000000000010011 $
b00000000000000000000000000010100 &
#39
#40
b00000000000000000000000000010100 $
b00000000000000000000000000010101 &
#41
#42
b00000000000000000000000000010101 $
b00000000000000000000000000010110 &
#43
#44
b00000000000000000000000000010110 $
b00000000000000000000000000010111 &
#45
#46
b00000000000000000000000000010111 $
b00000000000000000000000000011000 &
#47
#48
b00000000000000000000000000011000 $
b00000000000000000000000000011001 &
#49
#50
b00000000000000000000000000011001 $
b00000000000000000000000000011010 &
#51
#52
b00000000000000000000000000011010 $
b00000000000000000000000000011011 &
#53
#54
b00000000000000000000000000011011 $
b00000000000000000000000000011100 &
#55
#56
b00000000000000000000000000011100 $
b00000000000000000000000000011101 &
#57
#58
b00000000000000000000000000011101 $
b00000000000000000000000000011110 &
#59
#60
b00000000000000000000000000011110 $
b00000000000000000000000000011111 &
#61
#62
b00000000000000000000000000011111 $
b00000000000000000000000000100000 &
#63
#64
b00000000000000000000000000100000 $
b00000000000000000000000000100001 &
#65
#66
b00000000000000000000000000100001 $
b00000000000000000000000000100010 &
#67
#68
b00000000000000000000000000100010 $
b00000000000000000000000000100011 &
#69
#70
b00000000000000000000000000100011 $
b00000000000000000000000000100100 &
#71
#72
b00000000000000000000000000100100 $
b00000000000000000000000000100101 &
#73
#74
b00000000000000000000000000100101 $
b00000000000000000000000000100110 &
#75
#76
b00000000000000000000000000100110 $
b00000000000000000000000000100111 &
#77
#78
b00000000000000000000000000100111 $
b00000000000000000000000000101000 &
#79
#80
b00000000000000000000000000101000 $
b00000000000000000000000000101001 &
#81
#82
b00000000000000000000000000101001 $
b00000000000000000000000000101010 &
#83
#84
b00000000000000000000000000101010 $
b00000000000000000000000000101011 &
#85
#86
b00000000000000000000000000101011 $
b00000000000000000000000000101100 &
#87
#88
b00000000000000000000000000101100 $
b00000000000000000000000000101101 &
#89
#90
b00000000000000000000000000101101 $
b00000000000000000000000000101110 &
#91
#92
b00000000000000000000000000101110 $
b00000000000000000000000000101111 &
#93
#94
b00000000000000000000000000101111 $
b00000000000000000000000000110000 &
#95
#96
b00000000000000000000000000110000 $
b00000000000000000000000000110001 &
#97
#98
b00000000000000000000000000110001 $
b00000000000000000000000000110010 &
#99
#100
b00000000000000000000000000110010 $
b00000000000000000000000000110011 &
#101
#102
b00000000000000000000000000110011 $
b00000000000000000000000000110100 &
#103
#104
b00000000000000000000000000110100 $
b00000000000000000000000000110101 &
#105
#106
b00000000000000000000000000110101 $
b00000000000000000000000000110110 &
#107
#108
b00000000000000000000000000110110 $
b00000000000000000000000000110111 &
#109
#110
b00000000000000000000000000110111 $
b00000000000000000000000000111000 &
#111
#112
b00000000000000000000000000111000 $
b00000000000000000000000000111001 &
#113
#114
b00000000000000000000000000111001 $
b00000000000000000000000000111010 &
#115
#116
b00000000000000000000000000111010 $
b00000000000000000000000000111011 &
#117
#118
b00000000000000000000000000111011 $
b00000000000000000000000000111100 &
#119
#120
b00000000000000000000000000111100 $
b00000000000000000000000000111101 &
#121
#122
b00000000000000000000000000111101 $
b00000000000000000000000000111110 &
#123
#124
b00000000000000000000000000111110 $
b00000000000000000000000000111111 &
#125
#126
b00000000000000000000000000111111 $
b00000000000000000000000001000000 &
#127
#128
b00000000000000000000000001000000 $
b00000000000000000000000001000001 &
#129
#130
b00000000000000000000000001000001 $
b00000000000000000000000001000010 &
#131
#132
b00000000000000000000000001000010 $
b00000000000000000000000001000011 &
#133
#134
b00000000000000000000000001000011 $
b00000000000000000000000001000100 &
#135
#136
b00000000000000000000000001000100 $
b00000000000000000000000001000101 &
#137
#138
b00000000000000000000000001000101 $
b00000000000000000000000001000110 &
#139
#140
b00000000000000000000000001000110 $
b00000000000000000000000001000111 &
#141
#142
b00000000000000000000000001000111 $
b00000000000000000000000001001000 &
#143
#144
b00000000000000000000000001001000 $
b00000000000000000000000001001001 &
#145
#146
b00000000000000000000000001001001 $
b00000000000000000000000001001010 &
#147
#148
b00000000000000000000000001001010 $
b00000000000000000000000001001011 &
#149
#150
b00000000000000000000000001001011 $
b00000000000000000000000001001100 &
#151
#152
b00000000000000000000000001001100 $
b00000000000000000000000001001101 &
#153
#154
b00000000000000000000000001001101 $
b00000000000000000000000001001110 &
#155
#156
b00000000000000000000000001001110 $
b00000000000000000000000001001111 &
#157
#158
b00000000000000000000000001001111 $
b00000000000000000000000001010000 &
#159
#160
b00000000000000000000000001010000 $
b00000000000000000000000001010001 &
#161
#162
b00000000000000000000000001010001 $
b00000000000000000000000001010010 &
#163
#164
b00000000000000000000000001010010 $
b00000000000000000000000001010011 &
#165
#166
b00000000000000000000000001010011 $
b00000000000000000000000001010100 &
#167
#168
b00000000000000000000000001010100 $
b00000000000000000000000001010101 &
#169
#170
b00000000000000000000000001010101 $
b00000000000000000000000001010110 &
#171
#172
b00000000000000000000000001010110 $
b00000000000000000000000001010111 &
#173
#174
b00000000000000000000000001010111 $
b00000000000000000000000001011000 &
#175
#176
b00000000000000000000000001011000 $
b00000000000000000000000001011001 &
#177
#178
b00000000000000000000000001011001 $
b00000000000000000000000001011010 &
#179
#180
b00000000000000000000000001011010 $
b00000000000000000000000001011011 &
#181
#182
b00000000000000000000000001011011 $
b00000000000000000000000001011100 &
#183
#184
b00000000000000000000000001011100 $
b00000000000000000000000001011101 &
#185
#186
b00000000000000000000000001011101 $
b00000000000000000000000001011110 &
#187
#188
b00000000000000000000000001011110 $
b00000000000000000000000001011111 &
#189
#190
b00000000000000000000000001011111 $
b00000000000000000000000001100000 &
#191
#192
b00000000000000000000000001100000 $
b00000000000000000000000001100001 &
#193
#194
b00000000000000000000000001100001 $
b00000000000000000000000001100010 &
#195
#196
b00000000000000000000000001100010 $
b00000000000000000000000001100011 &
#197
#198
b00000000000000000000000001100011 $
b00000000000000000000000001100100 &
#199
#200
b00000000000000000000000001100100 $
b00000000000000000000000001100101 &
#201
#202
b00000000000000000000000001100101 $
b00000000000000000000000001100110 &
#203
#204
b00000000000000000000000001100110 $
b00000000000000000000000001100111 &
#205
#206
b00000000000000000000000001100111 $
b00000000000000000000000001101000 &
#207
#208
b00000000000000000000000001101000 $
b00000000000000000000000001101001 &
#209
#210
b00000000000000000000000001101001 $
b00000000000000000000000001101010 &
#211
#212
b00000000000000000000000001101010 $
b00000000000000000000000001101011 &
#213
#214
b00000000000000000000000001101011 $
b00000000000000000000000001101100 &
#215
#216
b00000000000000000000000001101100 $
b00000000000000000000000001101101 &
#217
#218
b00000000000000000000000001101101 $
b00000000000000000000000001101110 &
#219
#220
b00000000000000000000000001101110 $
b00000000000000000000000001101111 &
#221
#222
b00000000000000000000000001101111 $
b00000000000000000000000001110000 &
#223
#224
b00000000000000000000000001110000 $
b00000000000000000000000001110001 &
#225
#226
b00000000000000000000000001110001 $
b00000000000000000000000001110010 &
#227
#228
b00000000000000000000000001110010 $
b00000000000000000000000001110011 &
#229
#230
b00000000000000000000000001110011 $
b00000000000000000000000001110100 &
#231
#232
b00000000000000000000000001110100 $
b00000000000000000000000001110101 &
#233
#234
b00000000000000000000000001110101 $
b00000000000000000000000001110110 &
#235
#236
b00000000000000000000000001110110 $
b00000000000000000000000001110111 &
#237
#238
b00000000000000000000000001110111 $
b00000000000000000000000001111000 &
#239
#240
b00000000000000000000000001111000 $
b00000000000000000000000001111001 &
#241
#242
b00000000000000000000000001111001 $
b00000000000000000000000001111010 &
#243
#244
b00000000000000000000000001111010 $
b00000000000000000000000001111011 &
#245
#246
b00000000000000000000000001111011 $
b00000000000000000000000001111100 &
#247
#248
b00000000000000000000000001111100 $
b00000000000000000000000001111101 &
#249
#250
b00000000000000000000000001111101 $
b00000000000000000000000001111110 &
#251
#252
b00000000000000000000000001111110 $
b00000000000000000000000001111111 &
#253
#254
b00000000000000000000000001111111 $
b00000000000000000000000010000000 &
#255
#256
b00000000000000000000000010000000 $
b00000000000000000000000010000001 &
#257
#258
b00000000000000000000000010000001 $
b00000000000000000000000010000010 &
#259
#260
b00000000000000000000000010000010 $
b00000000000000000000000010000011 &
#261
#262
b00000000000000000000000010000011 $
b00000000000000000000000010000100 &
#263
#264
b00000000000000000000000010000100 $
b00000000000000000000000010000101 &
#265
#266
b00000000000000000000000010000101 $
b00000000000000000000000010000110 &
#267
#268
b00000000000000000000000010000110 $
b00000000000000000000000010000111 &
#269
#270
b00000000000000000000000010000111 $
b00000000000000000000000010001000 &
#271
#272
b00000000000000000000000010001000 $
b00000000000000000000000010001001 &
#273
#274
b00000000000000000000000010001001 $
b00000000000000000000000010001010 &
#275
#276
b00000000000000000000000010001010 $
b00000000000000000000000010001011 &
#277
#278
b00000000000000000000000010001011 $
b00000000000000000000000010001100 &
#279
#280
b00000000000000000000000010001100 $
b00000000000000000000000010001101 &
#281
#282
b00000000000000000000000010001101 $
b00000000000000000000000010001110 &
#283
#284
b00000000000000000000000010001110 $
b00000000000000000000000010001111 &
#285
#286
b00000000000000000000000010001111 $
b00000000000000000000000010010000 &
#287
#288
b00000000000000000000000010010000 $
b00000000000000000000000010010001 &
#289
#290
b00000000000000000000000010010001 $
b00000000000000000000000010010010 &
#291
#292
b00000000000000000000000010010010 $
b00000000000000000000000010010011 &
#293
#294
b00000000000000000000000010010011 $
b00000000000000000000000010010100 &
#295
#296
b00000000000000000000000010010100 $
b00000000000000000000000010010101 &
#297
#298
b00000000000000000000000010010101 $
b00000000000000000000000010010110 &
#299
#300
b00000000000000000000000010010110 $
b00000000000000000000000010010111 &
#301
#302
b00000000000000000000000010010111 $
b00000000000000000000000010011000 &
#303
#304
b00000000000000000000000010011000 $
b00000000000000000000000010011001 &
#305
#306
b00000000000000000000000010011001 $
b00000000000000000000000010011010 &
#307
#308
b00000000000000000000000010011010 $
b00000000000000000000000010011011 &
#309
#310
b00000000000000000000000010011011 $
b00000000000000000000000010011100 &
#311
#312
b00000000000000000000000010011100 $
b00000000000000000000000010011101 &
#313
#314
b00000000000000000000000010011101 $
b00000000000000000000000010011110 &
#315
#316
b00000000000000000000000010011110 $
b00000000000000000000000010011111 &
#317
#318
b00000000000000000000000010011111 $
b00000000000000000000000010100000 &
#319
#320
b00000000000000000000000010100000 $
b00000000000000000000000010100001 &
#321
#322
b00000000000000000000000010100001 $
b00000000000000000000000010100010 &
#323
#324
b00000000000000000000000010100010 $
b00000000000000000000000010100011 &
#325
#326
b00000000000000000000000010100011 $
b00000000000000000000000010100100 &
#327
#328
b00000000000000000000000010100100 $
b00000000000000000000000010100101 &
#329
#330
b00000000000000000000000010100101 $
b00000000000000000000000010100110 &
#331
#332
b00000000000000000000000010100110 $
b00000000000000000000000010100111 &
#333
#334
b00000000000000000000000010100111 $
b00000000000000000000000010101000 &
#335
#336
b00000000000000000000000010101000 $
b00000000000000000000000010101001 &
#337
#338
b00000000000000000000000010101001 $
b00000000000000000000000010101010 &
#339
#340
b00000000000000000000000010101010 $
b00000000000000000000000010101011 &
#341
#342
b00000000000000000000000010101011 $
b00000000000000000000000010101100 &
#343
#344
b00000000000000000000000010101100 $
b00000000000000000000000010101101 &
#345
#346
b00000000000000000000000010101101 $
b00000000000000000000000010101110 &
#347
#348
b00000000000000000000000010101110 $
b00000000000000000000000010101111 &
#349
#350
b00000000000000000000000010101111 $
b00000000000000000000000010110000 &
#351
#352
b00000000000000000000000010110000 $
b00000000000000000000000010110001 &
#353
#354
b00000000000000000000000010110001 $
b00000000000000000000000010110010 &
#355
#356
b00000000000000000000000010110010 $
b00000000000000000000000010110011 &
#357
#358
b00000000000000000000000010110011 $
b00000000000000000000000010110100 &
#359
#360
b00000000000000000000000010110100 $
b00000000000000000000000010110101 &
#361
#362
b00000000000000000000000010110101 $
b00000000000000000000000010110110 &
#363
#364
b00000000000000000000000010110110 $
b00000000000000000000000010110111 &
#365
#366
b00000000000000000000000010110111 $
b00000000000000000000000010111000 &
#367
#368
b00000000000000000000000010111000 $
b00000000000000000000000010111001 &
#369
#370
b00000000000000000000000010111001 $
b00000000000000000000000010111010 &
#371
#372
b00000000000000000000000010111010 $
b00000000000000000000000010111011 &
#373
#374
b00000000000000000000000010111011 $
b00000000000000000000000010111100 &
#375
#376
b00000000000000000000000010111100 $
b00000000000000000000000010111101 &
#377
#378
b00000000000000000000000010111101 $
b00000000000000000000000010111110 &
#379
#380
b00000000000000000000000010111110 $
b00000000000000000000000010111111 &
#381
#382
b00000000000000000000000010111111 $
b00000000000000000000000011000000 &
#383
#384
b00000000000000000000000011000000 $
b00000000000000000000000011000001 &
#385
#386
b00000000000000000000000011000001 $
b00000000000000000000000011000010 &
#387
#388
b00000000000000000000000011000010 $
b00000000000000000000000011000011 &
#389
#390
b00000000000000000000000011000011 $
b00000000000000000000000011000100 &
#391
#392
b00000000000000000000000011000100 $
b00000000000000000000000011000101 &
#393
#394
b00000000000000000000000011000101 $
b00000000000000000000000011000110 &
#395
#396
b00000000000000000000000011000110 $
b00000000000000000000000011000111 &
#397
#398
b00000000000000000000000011000111 $
b00000000000000000000000011001000 &
#399
#400
b00000000000000000000000011001000 $
b00000000000000000000000011001001 &
#401
#402
b00000000000000000000000011001001 $
b00000000000000000000000011001010 &
#403
#404
b00000000000000000000000011001010 $
b00000000000000000000000011001011 &
#405
#406
b00000000000000000000000011001011 $
b00000000000000000000000011001100 &
#407
#408
b00000000000000000000000011001100 $
b00000000000000000000000011001101 &
#409
#410
b00000000000000000000000011001101 $
b00000000000000000000000011001110 &
#411
#412
b00000000000000000000000011001110 $
b00000000000000000000000011001111 &
#413
#414
b00000000000000000000000011001111 $
b00000000000000000000000011010000 &
#415
#416
b00000000000000000000000011010000 $
b00000000000000000000000011010001 &
#417
#418
b00000000000000000000000011010001 $
b00000000000000000000000011010010 &
#419
#420
b00000000000000000000000011010010 $
b00000000000000000000000011010011 &
#421
#422
b00000000000000000000000011010011 $
b00000000000000000000000011010100 &
#423
#424
b00000000000000000000000011010100 $
b00000000000000000000000011010101 &
#425
#426
b00000000000000000000000011010101 $
b00000000000000000000000011010110 &
#427
#428
b00000000000000000000000011010110 $
b00000000000000000000000011010111 &
#429
#430
b00000000000000000000000011010111 $
b00000000000000000000000011011000 &
#431
#432
b00000000000000000000000011011000 $
b00000000000000000000000011011001 &
#433
#434
b00000000000000000000000011011001 $
b00000000000000000000000011011010 &
#435
#436
b00000000000000000000000011011010 $
b00000000000000000000000011011011 &
#437
#438
b00000000000000000000000011011011 $
b00000000000000000000000011011100 &
#439
#440
b00000000000000000000000011011100 $
b00000000000000000000000011011101 &
#441
#442
b00000000000000000000000011011101 $
b00000000000000000000000011011110 &
#443
#444
b00000000000000000000000011011110 $
b00000000000000000000000011011111 &
#445
#446
b00000000000000000000000011011111 $
b00000000000000000000000011100000 &
#447
#448
b00000000000000000000000011100000 $
b00000000000000000000000011100001 &
#449
#450
b00000000000000000000000011100001 $
b00000000000000000000000011100010 &
#451
#452
b00000000000000000000000011100010 $
b00000000000000000000000011100011 &
#453
#454
b00000000000000000000000011100011 $
b00000000000000000000000011100100 &
#455
#456
b00000000000000000000000011100100 $
b00000000000000000000000011100101 &
#457
#458
b00000000000000000000000011100101 $
b00000000000000000000000011100110 &
#459
#460
b00000000000000000000000011100110 $
b00000000000000000000000011100111 &
#461
#462
b00000000000000000000000011100111 $
b00000000000000000000000011101000 &
#463
#464
b00000000000000000000000011101000 $
b00000000000000000000000011101001 &
#465
#466
b00000000000000000000000011101001 $
b00000000000000000000000011101010 &
#467
#468
b00000000000000000000000011101010 $
b00000000000000000000000011101011 &
#469
#470
b00000000000000000000000011101011 $
b00000000000000000000000011101100 &
#471
#472
b00000000000000000000000011101100 $
b00000000000000000000000011101101 &
#473
#474
b00000000000000000000000011101101 $
b00000000000000000000000011101110 &
#475
#476
b00000000000000000000000011101110 $
b00000000000000000000000011101111 &
#477
#478
b00000000000000000000000011101111 $
b00000000000000000000000011110000 &
#479
#480
b00000000000000000000000011110000 $
b00000000000000000000000011110001 &
#481
#482
b00000000000000000000000011110001 $
b00000000000000000000000011110010 &
#483
#484
b00000000000000000000000011110010 $
b00000000000000000000000011110011 &
#485
#486
b00000000000000000000000011110011 $
b00000000000000000000000011110100 &
#487
#488
b00000000000000000000000011110100 $
b00000000000000000000000011110101 &
#489
#490
b00000000000000000000000011110101 $
b00000000000000000000000011110110 &
#491
#492
b00000000000000000000000011110110 $
b00000000000000000000000011110111 &
#493
#494
b00000000000000000000000011110111 $
b00000000000000000000000011111000 &
#495
#496
b00000000000000000000000011111000 $
b00000000000000000000000011111001 &
#497
#498
b00000000000000000000000011111001 $
b00000000000000000000000011111010 &
#499
#500
b00000000000000000000000011111010 $
b00000000000000000000000011111011 &
#501
#502
b00000000000000000000000011111011 $
b00000000000000000000000011111100 &
#503
#504
b00000000000000000000000011111100 $
b00000000000000000000000011111101 &
#505
#506
b00000000000000000000000011111101 $
b00000000000000000000000011111110 &
#507
#508
b00000000000000000000000011111110 $
b00000000000000000000000011111111 &
#509
#510
b00000000000000000000000011111111 $
b00000000000000000000000100000000 &
#511
#512
b00000000000000000000000100000000 $
b00000000000000000000000100000001 &
#513
#514
b00000000000000000000000100000001 $
b00000000000000000000000100000010 &
#515
#516
b00000000000000000000000100000010 $
b00000000000000000000000100000011 &
#517
#518
b00000000000000000000000100000011 $
b00000000000000000000000100000100 &
#519
#520
b00000000000000000000000100000100 $
b00000000000000000000000100000101 &
#521
#522
b00000000000000000000000100000101 $
b00000000000000000000000100000110 &
#523
#524
b00000000000000000000000100000110 $
b00000000000000000000000100000111 &
#525
#526
b00000000000000000000000100000111 $
b00000000000000000000000100001000 &
#527
#528
b00000000000000000000000100001000 $
b00000000000000000000000100001001 &
#529
#530
b00000000000000000000000100001001 $
b00000000000000000000000100001010 &
#531
#532
b00000000000000000000000100001010 $
b00000000000000000000000100001011 &
#533
#534
b00000000000000000000000100001011 $
b00000000000000000000000100001100 &
#535
#536
b00000000000000000000000100001100 $
b00000000000000000000000100001101 &
#537
#538
b00000000000000000000000100001101 $
b00000000000000000000000100001110 &
#539
#540
b00000000000000000000000100001110 $
b00000000000000000000000100001111 &
#541
#542
b00000000000000000000000100001111 $
b00000000000000000000000100010000 &
#543
#544
b00000000000000000000000100010000 $
b00000000000000000000000100010001 &
#545
#546
b00000000000000000000000100010001 $
b00000000000000000000000100010010 &
#547
#548
b00000000000000000000000100010010 $
b00000000000000000000000100010011 &
#549
#550
b00000000000000000000000100010011 $
b00000000000000000000000100010100 &
#551
#552
b00000000000000000000000100010100 $
b00000000000000000000000100010101 &
#553
#554
b00000000000000000000000100010101 $
b00000000000000000000000100010110 &
#555
#556
b00000000000000000000000100010110 $
b00000000000000000000000100010111 &
#557
#558
b00000000000000000000000100010111 $
b00000000000000000000000100011000 &
#559
#560
b00000000000000000000000100011000 $
b00000000000000000000000100011001 &
#561
#562
b00000000000000000000000100011001 $
b00000000000000000000000100011010 &
#563
#564
b00000000000000000000000100011010 $
b00000000000000000000000100011011 &
#565
#566
b00000000000000000000000100011011 $
b00000000000000000000000100011100 &
#567
#568
b00000000000000000000000100011100 $
b00000000000000000000000100011101 &
#569
#570
b00000000000000000000000100011101 $
b00000000000000000000000100011110 &
#571
#572
b00000000000000000000000100011110 $
b00000000000000000000000100011111 &
#573
#574
b00000000000000000000000100011111 $
b00000000000000000000000100100000 &
#575
#576
b00000000000000000000000100100000 $
b00000000000000000000000100100001 &
#577
#578
b00000000000000000000000100100001 $
b00000000000000000000000100100010 &
#579
#580
b00000000000000000000000100100010 $
b00000000000000000000000100100011 &
#581
#582
b00000000000000000000000100100011 $
b00000000000000000000000100100100 &
#583
#584
b00000000000000000000000100100100 $
b00000000000000000000000100100101 &
#585
#586
b00000000000000000000000100100101 $
b00000000000000000000000100100110 &
#587
#588
b00000000000000000000000100100110 $
b00000000000000000000000100100111 &
#589
#590
b00000000000000000000000100100111 $
b00000000000000000000000100101000 &
#591
#592
b00000000000000000000000100101000 $
b00000000000000000000000100101001 &
#593
#594
b00000000000000000000000100101001 $
b00000000000000000000000100101010 &
#595
#596
b00000000000000000000000100101010 $
b00000000000000000000000100101011 &
#597
#598
b00000000000000000000000100101011 $
b00000000000000000000000100101100 &
#599
#600
b00000000000000000000000100101100 $
b00000000000000000000000100101101 &
#601
#602
b00000000000000000000000100101101 $
b00000000000000000000000100101110 &
#603
#604
b00000000000000000000000100101110 $
b00000000000000000000000100101111 &
#605
#606
b00000000000000000000000100101111 $
b00000000000000000000000100110000 &
#607
#608
b00000000000000000000000100110000 $
b00000000000000000000000100110001 &
#609
#610
b00000000000000000000000100110001 $
b00000000000000000000000100110010 &
#611
#612
b00000000000000000000000100110010 $
b00000000000000000000000100110011 &
#613
#614
b00000000000000000000000100110011 $
b00000000000000000000000100110100 &
#615
#616
b00000000000000000000000100110100 $
b00000000000000000000000100110101 &
#617
#618
b00000000000000000000000100110101 $
b00000000000000000000000100110110 &
#619
#620
b00000000000000000000000100110110 $
b00000000000000000000000100110111 &
#621
#622
b00000000000000000000000100110111 $
b00000000000000000000000100111000 &
#623
#624
b00000000000000000000000100111000 $
b00000000000000000000000100111001 &
#625
#626
b00000000000000000000000100111001 $
b00000000000000000000000100111010 &
#627
#628
b00000000000000000000000100111010 $
b00000000000000000000000100111011 &
#629
#630
b00000000000000000000000100111011 $
b00000000000000000000000100111100 &
#631
#632
b00000000000000000000000100111100 $
b00000000000000000000000100111101 &
#633
#634
b00000000000000000000000100111101 $
b00000000000000000000000100111110 &
#635
#636
b00000000000000000000000100111110 $
b00000000000000000000000100111111 &
#637
#638
b00000000000000000000000100111111 $
b00000000000000000000000101000000 &
#639
#640
b00000000000000000000000101000000 $
b00000000000000000000000101000001 &
#641
#642
b00000000000000000000000101000001 $
b00000000000000000000000101000010 &
#643
#644
b00000000000000000000000101000010 $
b00000000000000000000000101000011 &
#645
#646
b00000000000000000000000101000011 $
b00000000000000000000000101000100 &
#647
#648
b00000000000000000000000101000100 $
b00000000000000000000000101000101 &
#649
#650
b00000000000000000000000101000101 $
b00000000000000000000000101000110 &
#651
#652
b00000000000000000000000101000110 $
b00000000000000000000000101000111 &
#653
#654
b00000000000000000000000101000111 $
b00000000000000000000000101001000 &
#655
#656
b00000000000000000000000101001000 $
b00000000000000000000000101001001 &
#657
#658
b00000000000000000000000101001001 $
b00000000000000000000000101001010 &
#659
#660
b00000000000000000000000101001010 $
b00000000000000000000000101001011 &
#661
#662
b00000000000000000000000101001011 $
b00000000000000000000000101001100 &
#663
#664
b00000000000000000000000101001100 $
b00000000000000000000000101001101 &
#665
#666
b00000000000000000000000101001101 $
b00000000000000000000000101001110 &
#667
#668
b00000000000000000000000101001110 $
b00000000000000000000000101001111 &
#669
#670
b00000000000000000000000101001111 $
b00000000000000000000000101010000 &
#671
#672
b00000000000000000000000101010000 $
b00000000000000000000000101010001 &
#673
#674
b00000000000000000000000101010001 $
b00000000000000000000000101010010 &
#675
#676
b00000000000000000000000101010010 $
b00000000000000000000000101010011 &
#677
#678
b00000000000000000000000101010011 $
b00000000000000000000000101010100 &
#679
#680
b00000000000000000000000101010100 $
b00000000000000000000000101010101 &
#681
#682
b00000000000000000000000101010101 $
b00000000000000000000000101010110 &
#683
#684
b00000000000000000000000101010110 $
b00000000000000000000000101010111 &
#685
#686
b00000000000000000000000101010111 $
b00000000000000000000000101011000 &
#687
#688
b00000000000000000000000101011000 $
b00000000000000000000000101011001 &
#689
#690
b00000000000000000000000101011001 $
b00000000000000000000000101011010 &
#691
#692
b00000000000000000000000101011010 $
b00000000000000000000000101011011 &
#693
#694
b00000000000000000000000101011011 $
b00000000000000000000000101011100 &
#695
#696
b00000000000000000000000101011100 $
b00000000000000000000000101011101 &
#697
#698
b00000000000000000000000101011101 $
b00000000000000000000000101011110 &
#699
#700
b00000000000000000000000101011110 $
b00000000000000000000000101011111 &
#701
#702
b00000000000000000000000101011111 $
b00000000000000000000000101100000 &
#703
#704
b00000000000000000000000101100000 $
b00000000000000000000000101100001 &
#705
#706
b00000000000000000000000101100001 $
b00000000000000000000000101100010 &
#707
#708
b00000000000000000000000101100010 $
b00000000000000000000000101100011 &
#709
#710
b00000000000000000000000101100011 $
b00000000000000000000000101100100 &
#711
#712
b00000000000000000000000101100100 $
b00000000000000000000000101100101 &
#713
#714
b00000000000000000000000101100101 $
b00000000000000000000000101100110 &
#715
#716
b00000000000000000000000101100110 $
b00000000000000000000000101100111 &
#717
#718
b00000000000000000000000101100111 $
b00000000000000000000000101101000 &
#719
#720
b00000000000000000000000101101000 $
b00000000000000000000000101101001 &
#721
#722
b00000000000000000000000101101001 $
b00000000000000000000000101101010 &
#723
#724
b00000000000000000000000101101010 $
b00000000000000000000000101101011 &
#725
#726
b00000000000000000000000101101011 $
b00000000000000000000000101101100 &
#727
#728
b00000000000000000000000101101100 $
b00000000000000000000000101101101 &
#729
#730
b00000000000000000000000101101101 $
b00000000000000000000000101101110 &
#731
#732
b00000000000000000000000101101110 $
b00000000000000000000000101101111 &
#733
#734
b00000000000000000000000101101111 $
b00000000000000000000000101110000 &
#735
#736
b00000000000000000000000101110000 $
b00000000000000000000000101110001 &
#737
#738
b00000000000000000000000101110001 $
b00000000000000000000000101110010 &
#739
#740
b00000000000000000000000101110010 $
b00000000000000000000000101110011 &
#741
#742
b00000000000000000000000101110011 $
b00000000000000000000000101110100 &
#743
#744
b00000000000000000000000101110100 $
b00000000000000000000000101110101 &
#745
#746
b00000000000000000000000101110101 $
b00000000000000000000000101110110 &
#747
#748
b00000000000000000000000101110110 $
b00000000000000000000000101110111 &
#749
#750
b00000000000000000000000101110111 $
b00000000000000000000000101111000 &
#751
#752
b00000000000000000000000101111000 $
b00000000000000000000000101111001 &
#753
#754
b00000000000000000000000101111001 $
b00000000000000000000000101111010 &
#755
#756
b00000000000000000000000101111010 $
b00000000000000000000000101111011 &
#757
#758
b00000000000000000000000101111011 $
b00000000000000000000000101111100 &
#759
#760
b00000000000000000000000101111100 $
b00000000000000000000000101111101 &
#761
#762
b00000000000000000000000101111101 $
b00000000000000000000000101111110 &
#763
#764
b00000000000000000000000101111110 $
b00000000000000000000000101111111 &
#765
#766
b00000000000000000000000101111111 $
b00000000000000000000000110000000 &
#767
#768
b00000000000000000000000110000000 $
b00000000000000000000000110000001 &
#769
#770
b00000000000000000000000110000001 $
b00000000000000000000000110000010 &
#771
#772
b00000000000000000000000110000010 $
b00000000000000000000000110000011 &
#773
#774
b00000000000000000000000110000011 $
b00000000000000000000000110000100 &
#775
#776
b00000000000000000000000110000100 $
b00000000000000000000000110000101 &
#777
#778
b00000000000000000000000110000101 $
b00000000000000000000000110000110 &
#779
#780
b00000000000000000000000110000110 $
b00000000000000000000000110000111 &
#781
#782
b00000000000000000000000110000111 $
b00000000000000000000000110001000 &
#783
#784
b00000000000000000000000110001000 $
b00000000000000000000000110001001 &
#785
#786
b00000000000000000000000110001001 $
b00000000000000000000000110001010 &
#787
#788
b00000000000000000000000110001010 $
b00000000000000000000000110001011 &
#789
#790
b00000000000000000000000110001011 $
b00000000000000000000000110001100 &
#791
#792
b00000000000000000000000110001100 $
b00000000000000000000000110001101 &
#793
#794
b00000000000000000000000110001101 $
b00000000000000000000000110001110 &
#795
#796
b00000000000000000000000110001110 $
b00000000000000000000000110001111 &
#797
#798
b00000000000000000000000110001111 $
b00000000000000000000000110010000 &
#799
#800
b00000000000000000000000110010000 $
b00000000000000000000000110010001 &
#801
#802
b00000000000000000000000110010001 $
b00000000000000000000000110010010 &
#803
